{"total_games": 11, "wins": 7, "wr": 0.6364, "items": [{"id": "2203", "name": "Silence Robe", "games": 3, "wins": 3, "wr": 1.0, "wlb": 0.4385}, {"id": "2201", "name": "Ares Belt", "games": 3, "wins": 3, "wr": 1.0, "wlb": 0.4385}, {"id": "0617014872193", "name": "Chastise Pauldron", "games": 7, "wins": 5, "wr": 0.7143, "wlb": 0.3589}, {"id": "1617054397404", "name": "Fleeting Time", "games": 11, "wins": 7, "wr": 0.6364, "wlb": 0.3538}, {"id": "3521", "name": "Tough Boots - Conceal", "games": 8, "wins": 5, "wr": 0.625, "wlb": 0.3057}, {"id": "3210", "name": "Radiant Armor", "games": 6, "wins": 4, "wr": 0.6667, "wlb": 0.3}, {"id": "3203", "name": "Antique Cuirass", "games": 1, "wins": 1, "wr": 1.0, "wlb": 0.2065}, {"id": "1202", "name": "Leather Jerkin", "games": 1, "wins": 1, "wr": 1.0, "wlb": 0.2065}, {"id": "3561", "name": "Rapid Boots- Conceal", "games": 1, "wins": 1, "wr": 1.0, "wlb": 0.2065}, {"id": "2205", "name": "Dreadnaught Armor", "games": 2, "wins": 1, "wr": 0.5, "wlb": 0.0945}, {"id": "3205", "name": "Athena's Shield", "games": 2, "wins": 1, "wr": 0.5, "wlb": 0.0945}, {"id": "3522", "name": "Tough Boots - Encourage", "games": 2, "wins": 1, "wr": 0.5, "wlb": 0.0945}, {"id": "2206", "name": "Steel Legplates", "games": 2, "wins": 1, "wr": 0.5, "wlb": 0.0945}, {"id": "1201", "name": "Vitality Crystal", "games": 2, "wins": 1, "wr": 0.5, "wlb": 0.0945}, {"id": "3206", "name": "Dominance Ice", "games": 3, "wins": 1, "wr": 0.3333, "wlb": 0.0615}, {"id": "3207", "name": "Immortality", "games": 1, "wins": 0, "wr": 0.0, "wlb": 0.0}], "item_combos": {"3": [{"items": ["Ares Belt", "Chastise Pauldron", "Fleeting Time"], "games": 3, "wins": 3, "wr": 1.0, "wlb": 0.4385}, {"items": ["Chastise Pauldron", "Fleeting Time", "Tough Boots - Conceal"], "games": 5, "wins": 4, "wr": 0.8, "wlb": 0.3755}, {"items": ["Ares Belt", "Chastise Pauldron", "Silence Robe"], "games": 2, "wins": 2, "wr": 1.0, "wlb": 0.3424}, {"items": ["Ares Belt", "Chastise Pauldron", "Tough Boots - Conceal"], "games": 2, "wins": 2, "wr": 1.0, "wlb": 0.3424}, {"items": ["Ares Belt", "Fleeting Time", "Silence Robe"], "games": 2, "wins": 2, "wr": 1.0, "wlb": 0.3424}, {"items": ["Ares Belt", "Fleeting Time", "Tough Boots - Conceal"], "games": 2, "wins": 2, "wr": 1.0, "wlb": 0.3424}, {"items": ["Chastise Pauldron", "Fleeting Time", "Silence Robe"], "games": 2, "wins": 2, "wr": 1.0, "wlb": 0.3424}, {"items": ["Chastise Pauldron", "Fleeting Time", "Radiant Armor"], "games": 4, "wins": 3, "wr": 0.75, "wlb": 0.3006}, {"items": ["Chastise Pauldron", "Radiant Armor", "Tough Boots - Conceal"], "games": 4, "wins": 3, "wr": 0.75, "wlb": 0.3006}, {"items": ["Fleeting Time", "Radiant Armor", "Tough Boots - Conceal"], "games": 6, "wins": 4, "wr": 0.6667, "wlb": 0.3}, {"items": ["Ares Belt", "Silence Robe", "Tough Boots - Conceal"], "games": 1, "wins": 1, "wr": 1.0, "wlb": 0.2065}, {"items": ["Chastise Pauldron", "Silence Robe", "Tough Boots - Conceal"], "games": 1, "wins": 1, "wr": 1.0, "wlb": 0.2065}, {"items": ["Fleeting Time", "Silence Robe", "Tough Boots - Conceal"], "games": 1, "wins": 1, "wr": 1.0, "wlb": 0.2065}, {"items": ["Antique Cuirass", "Athena's Shield", "Fleeting Time"], "games": 1, "wins": 1, "wr": 1.0, "wlb": 0.2065}, {"items": ["Antique Cuirass", "Athena's Shield", "Radiant Armor"], "games": 1, "wins": 1, "wr": 1.0, "wlb": 0.2065}, {"items": ["Antique Cuirass", "Athena's Shield", "Tough Boots - Conceal"], "games": 1, "wins": 1, "wr": 1.0, "wlb": 0.2065}, {"items": ["Antique Cuirass", "Fleeting Time", "Radiant Armor"], "games": 1, "wins": 1, "wr": 1.0, "wlb": 0.2065}, {"items": ["Antique Cuirass", "Fleeting Time", "Tough Boots - Conceal"], "games": 1, "wins": 1, "wr": 1.0, "wlb": 0.2065}, {"items": ["Antique Cuirass", "Radiant Armor", "Tough Boots - Conceal"], "games": 1, "wins": 1, "wr": 1.0, "wlb": 0.2065}, {"items": ["Athena's Shield", "Fleeting Time", "Radiant Armor"], "games": 1, "wins": 1, "wr": 1.0, "wlb": 0.2065}], "4": [{"items": ["Ares Belt", "Chastise Pauldron", "Fleeting Time", "Silence Robe"], "games": 2, "wins": 2, "wr": 1.0, "wlb": 0.3424}, {"items": ["Ares Belt", "Chastise Pauldron", "Fleeting Time", "Tough Boots - Conceal"], "games": 2, "wins": 2, "wr": 1.0, "wlb": 0.3424}, {"items": ["Chastise Pauldron", "Fleeting Time", "Radiant Armor", "Tough Boots - Conceal"], "games": 4, "wins": 3, "wr": 0.75, "wlb": 0.3006}, {"items": ["Ares Belt", "Chastise Pauldron", "Silence Robe", "Tough Boots - Conceal"], "games": 1, "wins": 1, "wr": 1.0, "wlb": 0.2065}, {"items": ["Ares Belt", "Fleeting Time", "Silence Robe", "Tough Boots - Conceal"], "games": 1, "wins": 1, "wr": 1.0, "wlb": 0.2065}, {"items": ["Chastise Pauldron", "Fleeting Time", "Silence Robe", "Tough Boots - Conceal"], "games": 1, "wins": 1, "wr": 1.0, "wlb": 0.2065}, {"items": ["Antique Cuirass", "Athena's Shield", "Fleeting Time", "Radiant Armor"], "games": 1, "wins": 1, "wr": 1.0, "wlb": 0.2065}, {"items": ["Antique Cuirass", "Athena's Shield", "Fleeting Time", "Tough Boots - Conceal"], "games": 1, "wins": 1, "wr": 1.0, "wlb": 0.2065}, {"items": ["Antique Cuirass", "Athena's Shield", "Radiant Armor", "Tough Boots - Conceal"], "games": 1, "wins": 1, "wr": 1.0, "wlb": 0.2065}, {"items": ["Antique Cuirass", "Fleeting Time", "Radiant Armor", "Tough Boots - Conceal"], "games": 1, "wins": 1, "wr": 1.0, "wlb": 0.2065}, {"items": ["Athena's Shield", "Fleeting Time", "Radiant Armor", "Tough Boots - Conceal"], "games": 1, "wins": 1, "wr": 1.0, "wlb": 0.2065}, {"items": ["Dreadnaught Armor", "Fleeting Time", "Leather Jerkin", "Silence Robe"], "games": 1, "wins": 1, "wr": 1.0, "wlb": 0.2065}, {"items": ["Dreadnaught Armor", "Fleeting Time", "Leather Jerkin", "Steel Legplates"], "games": 1, "wins": 1, "wr": 1.0, "wlb": 0.2065}, {"items": ["Dreadnaught Armor", "Fleeting Time", "Leather Jerkin", "Tough Boots - Encourage"], "games": 1, "wins": 1, "wr": 1.0, "wlb": 0.2065}, {"items": ["Dreadnaught Armor", "Fleeting Time", "Silence Robe", "Steel Legplates"], "games": 1, "wins": 1, "wr": 1.0, "wlb": 0.2065}, {"items": ["Dreadnaught Armor", "Fleeting Time", "Silence Robe", "Tough Boots - Encourage"], "games": 1, "wins": 1, "wr": 1.0, "wlb": 0.2065}, {"items": ["Dreadnaught Armor", "Fleeting Time", "Steel Legplates", "Tough Boots - Encourage"], "games": 1, "wins": 1, "wr": 1.0, "wlb": 0.2065}, {"items": ["Dreadnaught Armor", "Leather Jerkin", "Silence Robe", "Steel Legplates"], "games": 1, "wins": 1, "wr": 1.0, "wlb": 0.2065}, {"items": ["Dreadnaught Armor", "Leather Jerkin", "Silence Robe", "Tough Boots - Encourage"], "games": 1, "wins": 1, "wr": 1.0, "wlb": 0.2065}, {"items": ["Dreadnaught Armor", "Leather Jerkin", "Steel Legplates", "Tough Boots - Encourage"], "games": 1, "wins": 1, "wr": 1.0, "wlb": 0.2065}], "5": [{"items": ["Ares Belt", "Chastise Pauldron", "Fleeting Time", "Silence Robe", "Tough Boots - Conceal"], "games": 1, "wins": 1, "wr": 1.0, "wlb": 0.2065}, {"items": ["Antique Cuirass", "Athena's Shield", "Fleeting Time", "Radiant Armor", "Tough Boots - Conceal"], "games": 1, "wins": 1, "wr": 1.0, "wlb": 0.2065}, {"items": ["Dreadnaught Armor", "Fleeting Time", "Leather Jerkin", "Silence Robe", "Steel Legplates"], "games": 1, "wins": 1, "wr": 1.0, "wlb": 0.2065}, {"items": ["Dreadnaught Armor", "Fleeting Time", "Leather Jerkin", "Silence Robe", "Tough Boots - Encourage"], "games": 1, "wins": 1, "wr": 1.0, "wlb": 0.2065}, {"items": ["Dreadnaught Armor", "Fleeting Time", "Leather Jerkin", "Steel Legplates", "Tough Boots - Encourage"], "games": 1, "wins": 1, "wr": 1.0, "wlb": 0.2065}, {"items": ["Dreadnaught Armor", "Fleeting Time", "Silence Robe", "Steel Legplates", "Tough Boots - Encourage"], "games": 1, "wins": 1, "wr": 1.0, "wlb": 0.2065}, {"items": ["Dreadnaught Armor", "Leather Jerkin", "Silence Robe", "Steel Legplates", "Tough Boots - Encourage"], "games": 1, "wins": 1, "wr": 1.0, "wlb": 0.2065}, {"items": ["Fleeting Time", "Leather Jerkin", "Silence Robe", "Steel Legplates", "Tough Boots - Encourage"], "games": 1, "wins": 1, "wr": 1.0, "wlb": 0.2065}, {"items": ["Ares Belt", "Chastise Pauldron", "Fleeting Time", "Radiant Armor", "Tough Boots - Conceal"], "games": 1, "wins": 1, "wr": 1.0, "wlb": 0.2065}, {"items": ["Ares Belt", "Chastise Pauldron", "Fleeting Time", "Rapid Boots- Conceal", "Silence Robe"], "games": 1, "wins": 1, "wr": 1.0, "wlb": 0.2065}, {"items": ["Ares Belt", "Chastise Pauldron", "Fleeting Time", "Rapid Boots- Conceal", "Vitality Crystal"], "games": 1, "wins": 1, "wr": 1.0, "wlb": 0.2065}, {"items": ["Ares Belt", "Chastise Pauldron", "Fleeting Time", "Silence Robe", "Vitality Crystal"], "games": 1, "wins": 1, "wr": 1.0, "wlb": 0.2065}, {"items": ["Ares Belt", "Chastise Pauldron", "Rapid Boots- Conceal", "Silence Robe", "Vitality Crystal"], "games": 1, "wins": 1, "wr": 1.0, "wlb": 0.2065}, {"items": ["Ares Belt", "Fleeting Time", "Rapid Boots- Conceal", "Silence Robe", "Vitality Crystal"], "games": 1, "wins": 1, "wr": 1.0, "wlb": 0.2065}, {"items": ["Chastise Pauldron", "Fleeting Time", "Rapid Boots- Conceal", "Silence Robe", "Vitality Crystal"], "games": 1, "wins": 1, "wr": 1.0, "wlb": 0.2065}, {"items": ["Chastise Pauldron", "Dominance Ice", "Fleeting Time", "Radiant Armor", "Tough Boots - Conceal"], "games": 2, "wins": 1, "wr": 0.5, "wlb": 0.0945}, {"items": ["Chastise Pauldron", "Dominance Ice", "Dreadnaught Armor", "Fleeting Time", "Radiant Armor"], "games": 1, "wins": 0, "wr": 0.0, "wlb": 0.0}, {"items": ["Chastise Pauldron", "Dominance Ice", "Dreadnaught Armor", "Fleeting Time", "Tough Boots - Conceal"], "games": 1, "wins": 0, "wr": 0.0, "wlb": 0.0}, {"items": ["Chastise Pauldron", "Dominance Ice", "Dreadnaught Armor", "Radiant Armor", "Tough Boots - Conceal"], "games": 1, "wins": 0, "wr": 0.0, "wlb": 0.0}, {"items": ["Chastise Pauldron", "Dreadnaught Armor", "Fleeting Time", "Radiant Armor", "Tough Boots - Conceal"], "games": 1, "wins": 0, "wr": 0.0, "wlb": 0.0}], "6": [{"items": ["Dreadnaught Armor", "Fleeting Time", "Leather Jerkin", "Silence Robe", "Steel Legplates", "Tough Boots - Encourage"], "games": 1, "wins": 1, "wr": 1.0, "wlb": 0.2065}, {"items": ["Ares Belt", "Chastise Pauldron", "Fleeting Time", "Rapid Boots- Conceal", "Silence Robe", "Vitality Crystal"], "games": 1, "wins": 1, "wr": 1.0, "wlb": 0.2065}, {"items": ["Chastise Pauldron", "Dominance Ice", "Dreadnaught Armor", "Fleeting Time", "Radiant Armor", "Tough Boots - Conceal"], "games": 1, "wins": 0, "wr": 0.0, "wlb": 0.0}]}, "emblems": [{"id": "20003", "name": "Tank", "games": 11, "wins": 7, "wr": 0.6364, "wlb": 0.3538}], "talents": [{"id": "111", "name": "Thrill", "class": "Basic Common", "type": "standard", "games": 3, "wins": 3, "wr": 1.0, "wlb": 0.4385}, {"id": "331", "name": "Concussive Blast", "class": "Tank", "type": "core", "games": 11, "wins": 7, "wr": 0.6364, "wlb": 0.3538}, {"id": "121", "name": "Wilderness Blessing", "class": "Basic Common", "type": "standard", "games": 10, "wins": 6, "wr": 0.6, "wlb": 0.3127}, {"id": "811", "name": "Agility", "class": "Support", "type": "standard", "games": 4, "wins": 3, "wr": 0.75, "wlb": 0.3006}, {"id": "821", "name": "Pull Yourself Together", "class": "Support", "type": "standard", "games": 1, "wins": 1, "wr": 1.0, "wlb": 0.2065}, {"id": "311", "name": "Vitality", "class": "Tank", "type": "standard", "games": 1, "wins": 1, "wr": 1.0, "wlb": 0.2065}, {"id": "711", "name": "Firmness", "class": "Fighter", "type": "standard", "games": 2, "wins": 0, "wr": 0.0, "wlb": 0.0}, {"id": "611", "name": "Inspire", "class": "Mage", "type": "standard", "games": 1, "wins": 0, "wr": 0.0, "wlb": 0.0}], "emblem_talent_combos": [{"emblem_id": "20003", "emblem": "Tank", "talents": [{"id": "111", "name": "Thrill"}, {"id": "121", "name": "Wilderness Blessing"}, {"id": "331", "name": "Concussive Blast"}], "games": 3, "wins": 3, "wr": 1.0, "wlb": 0.4385}, {"emblem_id": "20003", "emblem": "Tank", "talents": [{"id": "121", "name": "Wilderness Blessing"}, {"id": "331", "name": "Concussive Blast"}, {"id": "811", "name": "Agility"}], "games": 3, "wins": 2, "wr": 0.6667, "wlb": 0.2077}, {"emblem_id": "20003", "emblem": "Tank", "talents": [{"id": "331", "name": "Concussive Blast"}, {"id": "811", "name": "Agility"}, {"id": "821", "name": "Pull Yourself Together"}], "games": 1, "wins": 1, "wr": 1.0, "wlb": 0.2065}, {"emblem_id": "20003", "emblem": "Tank", "talents": [{"id": "121", "name": "Wilderness Blessing"}, {"id": "311", "name": "Vitality"}, {"id": "331", "name": "Concussive Blast"}], "games": 1, "wins": 1, "wr": 1.0, "wlb": 0.2065}, {"emblem_id": "20003", "emblem": "Tank", "talents": [{"id": "121", "name": "Wilderness Blessing"}, {"id": "331", "name": "Concussive Blast"}, {"id": "711", "name": "Firmness"}], "games": 2, "wins": 0, "wr": 0.0, "wlb": 0.0}, {"emblem_id": "20003", "emblem": "Tank", "talents": [{"id": "121", "name": "Wilderness Blessing"}, {"id": "331", "name": "Concussive Blast"}, {"id": "611", "name": "Inspire"}], "games": 1, "wins": 0, "wr": 0.0, "wlb": 0.0}], "players": [{"name": "Lyoni", "games": 3, "wins": 2, "wr": 0.6667, "wlb": 0.2077, "top_build": ["Chastise Pauldron", "Dominance Ice", "Dreadnaught Armor", "Fleeting Time", "Radiant Armor", "Tough Boots - Conceal"], "top_emblem": "Tank", "top_talents": [{"id": "111", "name": "Thrill"}, {"id": "121", "name": "Wilderness Blessing"}, {"id": "331", "name": "Concussive Blast"}]}, {"name": "Kyy", "games": 2, "wins": 2, "wr": 1.0, "wlb": 0.3424, "top_build": ["Ares Belt", "Chastise Pauldron", "Fleeting Time", "Silence Robe", "Tough Boots - Conceal"], "top_emblem": "Tank", "top_talents": [{"id": "331", "name": "Concussive Blast"}, {"id": "811", "name": "Agility"}, {"id": "821", "name": "Pull Yourself Together"}]}, {"name": "Idok", "games": 2, "wins": 2, "wr": 1.0, "wlb": 0.3424, "top_build": ["Chastise Pauldron", "Fleeting Time", "Radiant Armor", "Tough Boots - Conceal"], "top_emblem": "Tank", "top_talents": [{"id": "121", "name": "Wilderness Blessing"}, {"id": "331", "name": "Concussive Blast"}, {"id": "811", "name": "Agility"}]}, {"name": "Perkziva", "games": 1, "wins": 1, "wr": 1.0, "wlb": 0.2065, "top_build": ["Ares Belt", "Chastise Pauldron", "Fleeting Time", "Rapid Boots- Conceal", "Silence Robe", "Vitality Crystal"], "top_emblem": "Tank", "top_talents": [{"id": "121", "name": "Wilderness Blessing"}, {"id": "311", "name": "Vitality"}, {"id": "331", "name": "Concussive Blast"}]}, {"name": "Baloyskie", "games": 1, "wins": 0, "wr": 0.0, "wlb": 0.0, "top_build": ["Chastise Pauldron", "Fleeting Time", "Tough Boots - Encourage"], "top_emblem": "Tank", "top_talents": [{"id": "121", "name": "Wilderness Blessing"}, {"id": "331", "name": "Concussive Blast"}, {"id": "811", "name": "Agility"}]}, {"name": "Finn", "games": 1, "wins": 0, "wr": 0.0, "wlb": 0.0, "top_build": ["Fleeting Time", "Radiant Armor", "Steel Legplates", "Tough Boots - Conceal", "Vitality Crystal"], "top_emblem": "Tank", "top_talents": [{"id": "121", "name": "Wilderness Blessing"}, {"id": "331", "name": "Concussive Blast"}, {"id": "711", "name": "Firmness"}]}, {"name": "Light", "games": 1, "wins": 0, "wr": 0.0, "wlb": 0.0, "top_build": ["Athena's Shield", "Dominance Ice", "Fleeting Time", "Immortality", "Tough Boots - Conceal"], "top_emblem": "Tank", "top_talents": [{"id": "121", "name": "Wilderness Blessing"}, {"id": "331", "name": "Concussive Blast"}, {"id": "611", "name": "Inspire"}]}], "name": "Chip", "slug": "chip", "portrait": "img/heroes/chip.png", "hero_id": "124"}