{"total_games": 27, "wins": 14, "wr": 0.5185, "items": [{"id": "3207", "name": "Immortality", "games": 9, "wins": 8, "wr": 0.8889, "wlb": 0.565}, {"id": "0617014872193", "name": "Chastise Pauldron", "games": 17, "wins": 11, "wr": 0.6471, "wlb": 0.413}, {"id": "3203", "name": "Antique Cuirass", "games": 9, "wins": 6, "wr": 0.6667, "wlb": 0.3542}, {"id": "3561", "name": "Rapid Boots- Conceal", "games": 2, "wins": 2, "wr": 1.0, "wlb": 0.3424}, {"id": "3521", "name": "Tough Boots - Conceal", "games": 12, "wins": 7, "wr": 0.5833, "wlb": 0.3195}, {"id": "3007", "name": "Blade of the Heptaseas", "games": 6, "wins": 4, "wr": 0.6667, "wlb": 0.3}, {"id": "3210", "name": "Radiant Armor", "games": 20, "wins": 10, "wr": 0.5, "wlb": 0.2993}, {"id": "2201", "name": "Ares Belt", "games": 9, "wins": 5, "wr": 0.5556, "wlb": 0.2666}, {"id": "3206", "name": "Dominance Ice", "games": 7, "wins": 4, "wr": 0.5714, "wlb": 0.2505}, {"id": "3205", "name": "Athena's Shield", "games": 10, "wins": 5, "wr": 0.5, "wlb": 0.2366}, {"id": "1201", "name": "Vitality Crystal", "games": 3, "wins": 2, "wr": 0.6667, "wlb": 0.2077}, {"id": "1620344127331", "name": "Winter crown", "games": 1, "wins": 1, "wr": 1.0, "wlb": 0.2065}, {"id": "2209", "name": "Thunder Belt", "games": 1, "wins": 1, "wr": 1.0, "wlb": 0.2065}, {"id": "3522", "name": "Tough Boots - Encourage", "games": 10, "wins": 4, "wr": 0.4, "wlb": 0.1682}, {"id": "1202", "name": "Leather Jerkin", "games": 6, "wins": 2, "wr": 0.3333, "wlb": 0.0968}, {"id": "2004", "name": "Fury hammer", "games": 6, "wins": 2, "wr": 0.3333, "wlb": 0.0968}, {"id": "2204", "name": "Black Ice Shield", "games": 2, "wins": 1, "wr": 0.5, "wlb": 0.0945}, {"id": "2302", "name": "Tough Boots", "games": 2, "wins": 1, "wr": 0.5, "wlb": 0.0945}, {"id": "2206", "name": "Steel Legplates", "games": 3, "wins": 1, "wr": 0.3333, "wlb": 0.0615}, {"id": "1203", "name": "Magic Resist Cloak", "games": 3, "wins": 0, "wr": 0.0, "wlb": 0.0}, {"id": "2205", "name": "Dreadnaught Armor", "games": 2, "wins": 0, "wr": 0.0, "wlb": 0.0}, {"id": "2207", "name": "Blade Armor", "games": 2, "wins": 0, "wr": 0.0, "wlb": 0.0}, {"id": "3202", "name": "Guardian Helmet", "games": 1, "wins": 0, "wr": 0.0, "wlb": 0.0}, {"id": "2203", "name": "Silence Robe", "games": 1, "wins": 0, "wr": 0.0, "wlb": 0.0}, {"id": "3012", "name": "Rose Gold Meteor", "games": 1, "wins": 0, "wr": 0.0, "wlb": 0.0}, {"id": "2301", "name": "Warrior Boots", "games": 1, "wins": 0, "wr": 0.0, "wlb": 0.0}], "item_combos": {"3": [{"items": ["Chastise Pauldron", "Immortality", "Tough Boots - Conceal"], "games": 6, "wins": 6, "wr": 1.0, "wlb": 0.6097}, {"items": ["Chastise Pauldron", "Immortality", "Radiant Armor"], "games": 4, "wins": 4, "wr": 1.0, "wlb": 0.5101}, {"items": ["Immortality", "Radiant Armor", "Tough Boots - Conceal"], "games": 4, "wins": 4, "wr": 1.0, "wlb": 0.5101}, {"items": ["Antique Cuirass", "Immortality", "Radiant Armor"], "games": 4, "wins": 4, "wr": 1.0, "wlb": 0.5101}, {"items": ["Chastise Pauldron", "Dominance Ice", "Immortality"], "games": 3, "wins": 3, "wr": 1.0, "wlb": 0.4385}, {"items": ["Chastise Pauldron", "Dominance Ice", "Tough Boots - Conceal"], "games": 3, "wins": 3, "wr": 1.0, "wlb": 0.4385}, {"items": ["Dominance Ice", "Immortality", "Radiant Armor"], "games": 3, "wins": 3, "wr": 1.0, "wlb": 0.4385}, {"items": ["Dominance Ice", "Immortality", "Tough Boots - Conceal"], "games": 3, "wins": 3, "wr": 1.0, "wlb": 0.4385}, {"items": ["Dominance Ice", "Radiant Armor", "Tough Boots - Conceal"], "games": 3, "wins": 3, "wr": 1.0, "wlb": 0.4385}, {"items": ["Antique Cuirass", "Chastise Pauldron", "Immortality"], "games": 3, "wins": 3, "wr": 1.0, "wlb": 0.4385}, {"items": ["Antique Cuirass", "Chastise Pauldron", "Radiant Armor"], "games": 3, "wins": 3, "wr": 1.0, "wlb": 0.4385}, {"items": ["Antique Cuirass", "Immortality", "Tough Boots - Conceal"], "games": 3, "wins": 3, "wr": 1.0, "wlb": 0.4385}, {"items": ["Chastise Pauldron", "Radiant Armor", "Tough Boots - Conceal"], "games": 6, "wins": 5, "wr": 0.8333, "wlb": 0.4365}, {"items": ["Ares Belt", "Blade of the Heptaseas", "Radiant Armor"], "games": 2, "wins": 2, "wr": 1.0, "wlb": 0.3424}, {"items": ["Athena's Shield", "Blade of the Heptaseas", "Immortality"], "games": 2, "wins": 2, "wr": 1.0, "wlb": 0.3424}, {"items": ["Athena's Shield", "Immortality", "Tough Boots - Conceal"], "games": 2, "wins": 2, "wr": 1.0, "wlb": 0.3424}, {"items": ["Blade of the Heptaseas", "Chastise Pauldron", "Immortality"], "games": 2, "wins": 2, "wr": 1.0, "wlb": 0.3424}, {"items": ["Blade of the Heptaseas", "Immortality", "Tough Boots - Conceal"], "games": 2, "wins": 2, "wr": 1.0, "wlb": 0.3424}, {"items": ["Ares Belt", "Athena's Shield", "Dominance Ice"], "games": 2, "wins": 2, "wr": 1.0, "wlb": 0.3424}, {"items": ["Ares Belt", "Athena's Shield", "Immortality"], "games": 2, "wins": 2, "wr": 1.0, "wlb": 0.3424}], "4": [{"items": ["Chastise Pauldron", "Immortality", "Radiant Armor", "Tough Boots - Conceal"], "games": 4, "wins": 4, "wr": 1.0, "wlb": 0.5101}, {"items": ["Chastise Pauldron", "Dominance Ice", "Immortality", "Radiant Armor"], "games": 3, "wins": 3, "wr": 1.0, "wlb": 0.4385}, {"items": ["Chastise Pauldron", "Dominance Ice", "Immortality", "Tough Boots - Conceal"], "games": 3, "wins": 3, "wr": 1.0, "wlb": 0.4385}, {"items": ["Chastise Pauldron", "Dominance Ice", "Radiant Armor", "Tough Boots - Conceal"], "games": 3, "wins": 3, "wr": 1.0, "wlb": 0.4385}, {"items": ["Dominance Ice", "Immortality", "Radiant Armor", "Tough Boots - Conceal"], "games": 3, "wins": 3, "wr": 1.0, "wlb": 0.4385}, {"items": ["Antique Cuirass", "Chastise Pauldron", "Immortality", "Radiant Armor"], "games": 3, "wins": 3, "wr": 1.0, "wlb": 0.4385}, {"items": ["Antique Cuirass", "Chastise Pauldron", "Immortality", "Tough Boots - Conceal"], "games": 3, "wins": 3, "wr": 1.0, "wlb": 0.4385}, {"items": ["Antique Cuirass", "Chastise Pauldron", "Radiant Armor", "Tough Boots - Conceal"], "games": 3, "wins": 3, "wr": 1.0, "wlb": 0.4385}, {"items": ["Antique Cuirass", "Immortality", "Radiant Armor", "Tough Boots - Conceal"], "games": 3, "wins": 3, "wr": 1.0, "wlb": 0.4385}, {"items": ["Athena's Shield", "Blade of the Heptaseas", "Chastise Pauldron", "Immortality"], "games": 2, "wins": 2, "wr": 1.0, "wlb": 0.3424}, {"items": ["Athena's Shield", "Blade of the Heptaseas", "Immortality", "Tough Boots - Conceal"], "games": 2, "wins": 2, "wr": 1.0, "wlb": 0.3424}, {"items": ["Athena's Shield", "Chastise Pauldron", "Immortality", "Tough Boots - Conceal"], "games": 2, "wins": 2, "wr": 1.0, "wlb": 0.3424}, {"items": ["Blade of the Heptaseas", "Chastise Pauldron", "Immortality", "Tough Boots - Conceal"], "games": 2, "wins": 2, "wr": 1.0, "wlb": 0.3424}, {"items": ["Ares Belt", "Athena's Shield", "Dominance Ice", "Immortality"], "games": 2, "wins": 2, "wr": 1.0, "wlb": 0.3424}, {"items": ["Ares Belt", "Athena's Shield", "Dominance Ice", "Rapid Boots- Conceal"], "games": 2, "wins": 2, "wr": 1.0, "wlb": 0.3424}, {"items": ["Ares Belt", "Athena's Shield", "Immortality", "Rapid Boots- Conceal"], "games": 2, "wins": 2, "wr": 1.0, "wlb": 0.3424}, {"items": ["Ares Belt", "Dominance Ice", "Immortality", "Rapid Boots- Conceal"], "games": 2, "wins": 2, "wr": 1.0, "wlb": 0.3424}, {"items": ["Antique Cuirass", "Chastise Pauldron", "Dominance Ice", "Immortality"], "games": 2, "wins": 2, "wr": 1.0, "wlb": 0.3424}, {"items": ["Antique Cuirass", "Chastise Pauldron", "Dominance Ice", "Radiant Armor"], "games": 2, "wins": 2, "wr": 1.0, "wlb": 0.3424}, {"items": ["Antique Cuirass", "Chastise Pauldron", "Dominance Ice", "Tough Boots - Conceal"], "games": 2, "wins": 2, "wr": 1.0, "wlb": 0.3424}], "5": [{"items": ["Chastise Pauldron", "Dominance Ice", "Immortality", "Radiant Armor", "Tough Boots - Conceal"], "games": 3, "wins": 3, "wr": 1.0, "wlb": 0.4385}, {"items": ["Antique Cuirass", "Chastise Pauldron", "Immortality", "Radiant Armor", "Tough Boots - Conceal"], "games": 3, "wins": 3, "wr": 1.0, "wlb": 0.4385}, {"items": ["Athena's Shield", "Blade of the Heptaseas", "Chastise Pauldron", "Immortality", "Tough Boots - Conceal"], "games": 2, "wins": 2, "wr": 1.0, "wlb": 0.3424}, {"items": ["Ares Belt", "Athena's Shield", "Dominance Ice", "Immortality", "Rapid Boots- Conceal"], "games": 2, "wins": 2, "wr": 1.0, "wlb": 0.3424}, {"items": ["Antique Cuirass", "Chastise Pauldron", "Dominance Ice", "Immortality", "Radiant Armor"], "games": 2, "wins": 2, "wr": 1.0, "wlb": 0.3424}, {"items": ["Antique Cuirass", "Chastise Pauldron", "Dominance Ice", "Immortality", "Tough Boots - Conceal"], "games": 2, "wins": 2, "wr": 1.0, "wlb": 0.3424}, {"items": ["Antique Cuirass", "Chastise Pauldron", "Dominance Ice", "Radiant Armor", "Tough Boots - Conceal"], "games": 2, "wins": 2, "wr": 1.0, "wlb": 0.3424}, {"items": ["Antique Cuirass", "Dominance Ice", "Immortality", "Radiant Armor", "Tough Boots - Conceal"], "games": 2, "wins": 2, "wr": 1.0, "wlb": 0.3424}, {"items": ["Antique Cuirass", "Athena's Shield", "Chastise Pauldron", "Fury hammer", "Tough Boots - Encourage"], "games": 1, "wins": 1, "wr": 1.0, "wlb": 0.2065}, {"items": ["Ares Belt", "Chastise Pauldron", "Leather Jerkin", "Radiant Armor", "Tough Boots - Encourage"], "games": 1, "wins": 1, "wr": 1.0, "wlb": 0.2065}, {"items": ["Ares Belt", "Chastise Pauldron", "Leather Jerkin", "Radiant Armor", "Vitality Crystal"], "games": 1, "wins": 1, "wr": 1.0, "wlb": 0.2065}, {"items": ["Ares Belt", "Chastise Pauldron", "Leather Jerkin", "Tough Boots - Encourage", "Vitality Crystal"], "games": 1, "wins": 1, "wr": 1.0, "wlb": 0.2065}, {"items": ["Ares Belt", "Chastise Pauldron", "Radiant Armor", "Tough Boots - Encourage", "Vitality Crystal"], "games": 1, "wins": 1, "wr": 1.0, "wlb": 0.2065}, {"items": ["Ares Belt", "Leather Jerkin", "Radiant Armor", "Tough Boots - Encourage", "Vitality Crystal"], "games": 1, "wins": 1, "wr": 1.0, "wlb": 0.2065}, {"items": ["Chastise Pauldron", "Leather Jerkin", "Radiant Armor", "Tough Boots - Encourage", "Vitality Crystal"], "games": 1, "wins": 1, "wr": 1.0, "wlb": 0.2065}, {"items": ["Antique Cuirass", "Immortality", "Radiant Armor", "Rapid Boots- Conceal", "Vitality Crystal"], "games": 1, "wins": 1, "wr": 1.0, "wlb": 0.2065}, {"items": ["Antique Cuirass", "Ares Belt", "Blade of the Heptaseas", "Radiant Armor", "Steel Legplates"], "games": 1, "wins": 1, "wr": 1.0, "wlb": 0.2065}, {"items": ["Antique Cuirass", "Ares Belt", "Blade of the Heptaseas", "Radiant Armor", "Tough Boots - Encourage"], "games": 1, "wins": 1, "wr": 1.0, "wlb": 0.2065}, {"items": ["Antique Cuirass", "Ares Belt", "Blade of the Heptaseas", "Steel Legplates", "Tough Boots - Encourage"], "games": 1, "wins": 1, "wr": 1.0, "wlb": 0.2065}, {"items": ["Antique Cuirass", "Ares Belt", "Radiant Armor", "Steel Legplates", "Tough Boots - Encourage"], "games": 1, "wins": 1, "wr": 1.0, "wlb": 0.2065}], "6": [{"items": ["Antique Cuirass", "Chastise Pauldron", "Dominance Ice", "Immortality", "Radiant Armor", "Tough Boots - Conceal"], "games": 2, "wins": 2, "wr": 1.0, "wlb": 0.3424}, {"items": ["Ares Belt", "Chastise Pauldron", "Leather Jerkin", "Radiant Armor", "Tough Boots - Encourage", "Vitality Crystal"], "games": 1, "wins": 1, "wr": 1.0, "wlb": 0.2065}, {"items": ["Antique Cuirass", "Ares Belt", "Blade of the Heptaseas", "Radiant Armor", "Steel Legplates", "Tough Boots - Encourage"], "games": 1, "wins": 1, "wr": 1.0, "wlb": 0.2065}, {"items": ["Athena's Shield", "Blade of the Heptaseas", "Chastise Pauldron", "Immortality", "Thunder Belt", "Tough Boots - Conceal"], "games": 1, "wins": 1, "wr": 1.0, "wlb": 0.2065}, {"items": ["Ares Belt", "Ares Belt", "Athena's Shield", "Dominance Ice", "Immortality", "Rapid Boots- Conceal"], "games": 1, "wins": 1, "wr": 1.0, "wlb": 0.2065}, {"items": ["Black Ice Shield", "Chastise Pauldron", "Fury hammer", "Leather Jerkin", "Radiant Armor", "Tough Boots - Conceal"], "games": 1, "wins": 1, "wr": 1.0, "wlb": 0.2065}, {"items": ["Ares Belt", "Athena's Shield", "Blade of the Heptaseas", "Chastise Pauldron", "Radiant Armor", "Tough Boots"], "games": 1, "wins": 1, "wr": 1.0, "wlb": 0.2065}, {"items": ["Antique Cuirass", "Ares Belt", "Athena's Shield", "Leather Jerkin", "Magic Resist Cloak", "Tough Boots - Conceal"], "games": 1, "wins": 0, "wr": 0.0, "wlb": 0.0}, {"items": ["Ares Belt", "Chastise Pauldron", "Leather Jerkin", "Magic Resist Cloak", "Radiant Armor", "Tough Boots - Conceal"], "games": 1, "wins": 0, "wr": 0.0, "wlb": 0.0}, {"items": ["Blade Armor", "Chastise Pauldron", "Dominance Ice", "Fury hammer", "Radiant Armor", "Tough Boots - Encourage"], "games": 1, "wins": 0, "wr": 0.0, "wlb": 0.0}, {"items": ["Antique Cuirass", "Athena's Shield", "Blade of the Heptaseas", "Chastise Pauldron", "Rose Gold Meteor", "Tough Boots - Conceal"], "games": 1, "wins": 0, "wr": 0.0, "wlb": 0.0}, {"items": ["Black Ice Shield", "Fury hammer", "Leather Jerkin", "Magic Resist Cloak", "Radiant Armor", "Tough Boots - Encourage"], "games": 1, "wins": 0, "wr": 0.0, "wlb": 0.0}, {"items": ["Athena's Shield", "Chastise Pauldron", "Leather Jerkin", "Radiant Armor", "Steel Legplates", "Warrior Boots"], "games": 1, "wins": 0, "wr": 0.0, "wlb": 0.0}]}, "emblems": [{"id": "20003", "name": "Tank", "games": 27, "wins": 14, "wr": 0.5185, "wlb": 0.3399}], "talents": [{"id": "331", "name": "Concussive Blast", "class": "Tank", "type": "core", "games": 27, "wins": 14, "wr": 0.5185, "wlb": 0.3399}, {"id": "121", "name": "Wilderness Blessing", "class": "Basic Common", "type": "standard", "games": 25, "wins": 13, "wr": 0.52, "wlb": 0.335}, {"id": "311", "name": "Vitality", "class": "Tank", "type": "standard", "games": 4, "wins": 3, "wr": 0.75, "wlb": 0.3006}, {"id": "111", "name": "Thrill", "class": "Basic Common", "type": "standard", "games": 21, "wins": 10, "wr": 0.4762, "wlb": 0.2834}, {"id": "521", "name": "Master Assassin", "class": "Assassin", "type": "standard", "games": 1, "wins": 1, "wr": 1.0, "wlb": 0.2065}, {"id": "811", "name": "Agility", "class": "Support", "type": "standard", "games": 2, "wins": 1, "wr": 0.5, "wlb": 0.0945}, {"id": "321", "name": "Tenacity", "class": "Tank", "type": "standard", "games": 1, "wins": 0, "wr": 0.0, "wlb": 0.0}], "emblem_talent_combos": [{"emblem_id": "20003", "emblem": "Tank", "talents": [{"id": "121", "name": "Wilderness Blessing"}, {"id": "311", "name": "Vitality"}, {"id": "331", "name": "Concussive Blast"}], "games": 4, "wins": 3, "wr": 0.75, "wlb": 0.3006}, {"emblem_id": "20003", "emblem": "Tank", "talents": [{"id": "111", "name": "Thrill"}, {"id": "121", "name": "Wilderness Blessing"}, {"id": "331", "name": "Concussive Blast"}], "games": 20, "wins": 9, "wr": 0.45, "wlb": 0.2582}, {"emblem_id": "20003", "emblem": "Tank", "talents": [{"id": "121", "name": "Wilderness Blessing"}, {"id": "331", "name": "Concussive Blast"}, {"id": "811", "name": "Agility"}], "games": 1, "wins": 1, "wr": 1.0, "wlb": 0.2065}, {"emblem_id": "20003", "emblem": "Tank", "talents": [{"id": "111", "name": "Thrill"}, {"id": "331", "name": "Concussive Blast"}, {"id": "521", "name": "Master Assassin"}], "games": 1, "wins": 1, "wr": 1.0, "wlb": 0.2065}, {"emblem_id": "20003", "emblem": "Tank", "talents": [{"id": "321", "name": "Tenacity"}, {"id": "331", "name": "Concussive Blast"}, {"id": "811", "name": "Agility"}], "games": 1, "wins": 0, "wr": 0.0, "wlb": 0.0}], "players": [{"name": "alekk", "games": 4, "wins": 3, "wr": 0.75, "wlb": 0.3006, "top_build": ["Ares Belt", "Chastise Pauldron", "Leather Jerkin", "Magic Resist Cloak", "Radiant Armor", "Tough Boots - Conceal"], "top_emblem": "Tank", "top_talents": [{"id": "121", "name": "Wilderness Blessing"}, {"id": "311", "name": "Vitality"}, {"id": "331", "name": "Concussive Blast"}]}, {"name": "Caloy", "games": 4, "wins": 3, "wr": 0.75, "wlb": 0.3006, "top_build": ["Antique Cuirass", "Chastise Pauldron", "Dominance Ice", "Immortality", "Radiant Armor", "Tough Boots - Conceal"], "top_emblem": "Tank", "top_talents": [{"id": "111", "name": "Thrill"}, {"id": "121", "name": "Wilderness Blessing"}, {"id": "331", "name": "Concussive Blast"}]}, {"name": "Nova_", "games": 3, "wins": 2, "wr": 0.6667, "wlb": 0.2077, "top_build": ["Antique Cuirass", "Ares Belt", "Blade of the Heptaseas", "Radiant Armor", "Steel Legplates", "Tough Boots - Encourage"], "top_emblem": "Tank", "top_talents": [{"id": "111", "name": "Thrill"}, {"id": "121", "name": "Wilderness Blessing"}, {"id": "331", "name": "Concussive Blast"}]}, {"name": "Owgwen", "games": 2, "wins": 2, "wr": 1.0, "wlb": 0.3424, "top_build": ["Athena's Shield", "Blade of the Heptaseas", "Chastise Pauldron", "Immortality", "Tough Boots - Conceal"], "top_emblem": "Tank", "top_talents": [{"id": "111", "name": "Thrill"}, {"id": "121", "name": "Wilderness Blessing"}, {"id": "331", "name": "Concussive Blast"}]}, {"name": "Lyoni", "games": 2, "wins": 1, "wr": 0.5, "wlb": 0.0945, "top_build": ["Antique Cuirass", "Athena's Shield", "Chastise Pauldron", "Fury hammer", "Tough Boots - Encourage"], "top_emblem": "Tank", "top_talents": [{"id": "111", "name": "Thrill"}, {"id": "121", "name": "Wilderness Blessing"}, {"id": "331", "name": "Concussive Blast"}]}, {"name": "Baloyskie", "games": 2, "wins": 0, "wr": 0.0, "wlb": 0.0, "top_build": ["Antique Cuirass", "Ares Belt", "Athena's Shield", "Leather Jerkin", "Magic Resist Cloak", "Tough Boots - Conceal"], "top_emblem": "Tank", "top_talents": [{"id": "111", "name": "Thrill"}, {"id": "121", "name": "Wilderness Blessing"}, {"id": "331", "name": "Concussive Blast"}]}, {"name": "Brusko", "games": 2, "wins": 0, "wr": 0.0, "wlb": 0.0, "top_build": ["Blade Armor", "Chastise Pauldron", "Dominance Ice", "Fury hammer", "Radiant Armor", "Tough Boots - Encourage"], "top_emblem": "Tank", "top_talents": [{"id": "111", "name": "Thrill"}, {"id": "121", "name": "Wilderness Blessing"}, {"id": "331", "name": "Concussive Blast"}]}, {"name": "Kyy", "games": 1, "wins": 1, "wr": 1.0, "wlb": 0.2065, "top_build": ["Chastise Pauldron", "Radiant Armor", "Tough Boots - Encourage", "Winter crown"], "top_emblem": "Tank", "top_talents": [{"id": "111", "name": "Thrill"}, {"id": "121", "name": "Wilderness Blessing"}, {"id": "331", "name": "Concussive Blast"}]}, {"name": "Muezza", "games": 1, "wins": 1, "wr": 1.0, "wlb": 0.2065, "top_build": ["Ares Belt", "Chastise Pauldron", "Leather Jerkin", "Radiant Armor", "Tough Boots - Encourage", "Vitality Crystal"], "top_emblem": "Tank", "top_talents": [{"id": "111", "name": "Thrill"}, {"id": "121", "name": "Wilderness Blessing"}, {"id": "331", "name": "Concussive Blast"}]}, {"name": "Kirk", "games": 1, "wins": 1, "wr": 1.0, "wlb": 0.2065, "top_build": ["Ares Belt", "Athena's Shield", "Blade of the Heptaseas", "Chastise Pauldron", "Radiant Armor", "Tough Boots"], "top_emblem": "Tank", "top_talents": [{"id": "111", "name": "Thrill"}, {"id": "331", "name": "Concussive Blast"}, {"id": "521", "name": "Master Assassin"}]}, {"name": "Aprho", "games": 1, "wins": 0, "wr": 0.0, "wlb": 0.0, "top_build": ["Antique Cuirass", "Blade of the Heptaseas", "Guardian Helmet", "Radiant Armor", "Tough Boots - Conceal"], "top_emblem": "Tank", "top_talents": [{"id": "111", "name": "Thrill"}, {"id": "121", "name": "Wilderness Blessing"}, {"id": "331", "name": "Concussive Blast"}]}, {"name": "Perkziva", "games": 1, "wins": 0, "wr": 0.0, "wlb": 0.0, "top_build": ["Chastise Pauldron", "Radiant Armor", "Tough Boots - Encourage"], "top_emblem": "Tank", "top_talents": [{"id": "111", "name": "Thrill"}, {"id": "121", "name": "Wilderness Blessing"}, {"id": "331", "name": "Concussive Blast"}]}, {"name": "Ch4knu", "games": 1, "wins": 0, "wr": 0.0, "wlb": 0.0, "top_build": ["Antique Cuirass", "Athena's Shield", "Blade of the Heptaseas", "Chastise Pauldron", "Rose Gold Meteor", "Tough Boots - Conceal"], "top_emblem": "Tank", "top_talents": [{"id": "121", "name": "Wilderness Blessing"}, {"id": "311", "name": "Vitality"}, {"id": "331", "name": "Concussive Blast"}]}, {"name": "Lansu", "games": 1, "wins": 0, "wr": 0.0, "wlb": 0.0, "top_build": ["Blade Armor", "Dominance Ice", "Fury hammer", "Radiant Armor", "Tough Boots"], "top_emblem": "Tank", "top_talents": [{"id": "111", "name": "Thrill"}, {"id": "121", "name": "Wilderness Blessing"}, {"id": "331", "name": "Concussive Blast"}]}, {"name": "Flap", "games": 1, "wins": 0, "wr": 0.0, "wlb": 0.0, "top_build": ["Athena's Shield", "Chastise Pauldron", "Leather Jerkin", "Radiant Armor", "Steel Legplates", "Warrior Boots"], "top_emblem": "Tank", "top_talents": [{"id": "321", "name": "Tenacity"}, {"id": "331", "name": "Concussive Blast"}, {"id": "811", "name": "Agility"}]}], "name": "Hilda", "slug": "hilda", "portrait": "img/heroes/hilda.png", "hero_id": "35"}