{"total_games": 3, "wins": 1, "wr": 0.3333, "items": [{"id": "3521", "name": "Tough Boots - Conceal", "games": 3, "wins": 1, "wr": 0.3333, "wlb": 0.0615}], "item_combos": {"3": [{"items": ["Dreadnaught Armor", "Silence Robe", "Tough Boots - Conceal"], "games": 2, "wins": 0, "wr": 0.0, "wlb": 0.0}], "4": [], "5": [], "6": []}, "emblems": [{"id": "20003", "name": "Tank", "games": 3, "wins": 1, "wr": 0.3333, "wlb": 0.0615}], "talents": [{"id": "111", "name": "Thrill", "class": "Basic Common", "type": "standard", "games": 3, "wins": 1, "wr": 0.3333, "wlb": 0.0615}, {"id": "121", "name": "Wilderness Blessing", "class": "Basic Common", "type": "standard", "games": 3, "wins": 1, "wr": 0.3333, "wlb": 0.0615}, {"id": "331", "name": "Concussive Blast", "class": "Tank", "type": "core", "games": 3, "wins": 1, "wr": 0.3333, "wlb": 0.0615}], "emblem_talent_combos": [{"emblem_id": "20003", "emblem": "Tank", "talents": [{"id": "111", "name": "Thrill"}, {"id": "121", "name": "Wilderness Blessing"}, {"id": "331", "name": "Concussive Blast"}], "games": 3, "wins": 1, "wr": 0.3333, "wlb": 0.0615}], "players": [{"name": "Ch4knu", "games": 1, "wins": 1, "wr": 1.0, "wlb": 0.2065, "top_build": ["Antique Cuirass", "Dagger", "Dominance Ice", "Immortality", "Radiant Armor", "Tough Boots - Conceal"], "top_emblem": "Tank", "top_talents": [{"id": "111", "name": "Thrill"}, {"id": "121", "name": "Wilderness Blessing"}, {"id": "331", "name": "Concussive Blast"}]}, {"name": "Jaypee", "games": 1, "wins": 0, "wr": 0.0, "wlb": 0.0, "top_build": ["Blade Armor", "Dreadnaught Armor", "Silence Robe", "Tough Boots - Conceal", "Vitality Crystal"], "top_emblem": "Tank", "top_talents": [{"id": "111", "name": "Thrill"}, {"id": "121", "name": "Wilderness Blessing"}, {"id": "331", "name": "Concussive Blast"}]}, {"name": "xNova", "games": 1, "wins": 0, "wr": 0.0, "wlb": 0.0, "top_build": ["Dreadnaught Armor", "Healing Necklace", "Immortality", "Magic Resist Cloak", "Silence Robe", "Tough Boots - Conceal"], "top_emblem": "Tank", "top_talents": [{"id": "111", "name": "Thrill"}, {"id": "121", "name": "Wilderness Blessing"}, {"id": "331", "name": "Concussive Blast"}]}], "name": "Jawhead", "slug": "jawhead", "portrait": "img/heroes/jawhead.png", "hero_id": "54"}