{"total_games": 30, "wins": 14, "wr": 0.4667, "items": [{"id": "2011", "name": "Wind of Nature", "games": 15, "wins": 9, "wr": 0.6, "wlb": 0.3575}, {"id": "2006", "name": "Demon Hunter Sword", "games": 29, "wins": 14, "wr": 0.4828, "wlb": 0.3139}, {"id": "2008", "name": "Corrosion Scythe", "games": 30, "wins": 14, "wr": 0.4667, "wlb": 0.3023}, {"id": "2009", "name": "Golden Staff", "games": 30, "wins": 14, "wr": 0.4667, "wlb": 0.3023}, {"id": "2301", "name": "Warrior Boots", "games": 18, "wins": 9, "wr": 0.5, "wlb": 0.2903}, {"id": "2302", "name": "Tough Boots", "games": 5, "wins": 3, "wr": 0.6, "wlb": 0.2307}, {"id": "1620354227288", "name": "Malefic Gun", "games": 17, "wins": 7, "wr": 0.4118, "wlb": 0.2161}, {"id": "3012", "name": "Rose Gold Meteor", "games": 11, "wins": 4, "wr": 0.3636, "wlb": 0.1517}, {"id": "2004", "name": "Fury hammer", "games": 4, "wins": 2, "wr": 0.5, "wlb": 0.15}, {"id": "1006", "name": "Regular Spear", "games": 4, "wins": 0, "wr": 0.0, "wlb": 0.0}, {"id": "1001", "name": "Dagger", "games": 3, "wins": 0, "wr": 0.0, "wlb": 0.0}], "item_combos": {"3": [{"items": ["Corrosion Scythe", "Warrior Boots", "Wind of Nature"], "games": 11, "wins": 8, "wr": 0.7273, "wlb": 0.4343}, {"items": ["Demon Hunter Sword", "Warrior Boots", "Wind of Nature"], "games": 11, "wins": 8, "wr": 0.7273, "wlb": 0.4343}, {"items": ["Golden Staff", "Warrior Boots", "Wind of Nature"], "games": 11, "wins": 8, "wr": 0.7273, "wlb": 0.4343}, {"items": ["Corrosion Scythe", "Demon Hunter Sword", "Wind of Nature"], "games": 15, "wins": 9, "wr": 0.6, "wlb": 0.3575}, {"items": ["Corrosion Scythe", "Golden Staff", "Wind of Nature"], "games": 15, "wins": 9, "wr": 0.6, "wlb": 0.3575}, {"items": ["Demon Hunter Sword", "Golden Staff", "Wind of Nature"], "games": 15, "wins": 9, "wr": 0.6, "wlb": 0.3575}, {"items": ["Corrosion Scythe", "Fury hammer", "Wind of Nature"], "games": 2, "wins": 2, "wr": 1.0, "wlb": 0.3424}, {"items": ["Demon Hunter Sword", "Fury hammer", "Wind of Nature"], "games": 2, "wins": 2, "wr": 1.0, "wlb": 0.3424}, {"items": ["Fury hammer", "Golden Staff", "Wind of Nature"], "games": 2, "wins": 2, "wr": 1.0, "wlb": 0.3424}, {"items": ["Fury hammer", "Warrior Boots", "Wind of Nature"], "games": 2, "wins": 2, "wr": 1.0, "wlb": 0.3424}, {"items": ["Corrosion Scythe", "Demon Hunter Sword", "Winter crown"], "games": 2, "wins": 2, "wr": 1.0, "wlb": 0.3424}, {"items": ["Corrosion Scythe", "Golden Staff", "Winter crown"], "games": 2, "wins": 2, "wr": 1.0, "wlb": 0.3424}, {"items": ["Corrosion Scythe", "Malefic Gun", "Winter crown"], "games": 2, "wins": 2, "wr": 1.0, "wlb": 0.3424}, {"items": ["Demon Hunter Sword", "Golden Staff", "Winter crown"], "games": 2, "wins": 2, "wr": 1.0, "wlb": 0.3424}, {"items": ["Demon Hunter Sword", "Malefic Gun", "Winter crown"], "games": 2, "wins": 2, "wr": 1.0, "wlb": 0.3424}, {"items": ["Golden Staff", "Malefic Gun", "Winter crown"], "games": 2, "wins": 2, "wr": 1.0, "wlb": 0.3424}, {"items": ["Corrosion Scythe", "Demon Hunter Sword", "Golden Staff"], "games": 29, "wins": 14, "wr": 0.4828, "wlb": 0.3139}, {"items": ["Corrosion Scythe", "Demon Hunter Sword", "Warrior Boots"], "games": 17, "wins": 9, "wr": 0.5294, "wlb": 0.3096}, {"items": ["Demon Hunter Sword", "Golden Staff", "Warrior Boots"], "games": 17, "wins": 9, "wr": 0.5294, "wlb": 0.3096}, {"items": ["Corrosion Scythe", "Golden Staff", "Warrior Boots"], "games": 18, "wins": 9, "wr": 0.5, "wlb": 0.2903}], "4": [{"items": ["Corrosion Scythe", "Demon Hunter Sword", "Warrior Boots", "Wind of Nature"], "games": 11, "wins": 8, "wr": 0.7273, "wlb": 0.4343}, {"items": ["Corrosion Scythe", "Golden Staff", "Warrior Boots", "Wind of Nature"], "games": 11, "wins": 8, "wr": 0.7273, "wlb": 0.4343}, {"items": ["Demon Hunter Sword", "Golden Staff", "Warrior Boots", "Wind of Nature"], "games": 11, "wins": 8, "wr": 0.7273, "wlb": 0.4343}, {"items": ["Corrosion Scythe", "Demon Hunter Sword", "Golden Staff", "Wind of Nature"], "games": 15, "wins": 9, "wr": 0.6, "wlb": 0.3575}, {"items": ["Corrosion Scythe", "Demon Hunter Sword", "Fury hammer", "Wind of Nature"], "games": 2, "wins": 2, "wr": 1.0, "wlb": 0.3424}, {"items": ["Corrosion Scythe", "Fury hammer", "Golden Staff", "Wind of Nature"], "games": 2, "wins": 2, "wr": 1.0, "wlb": 0.3424}, {"items": ["Corrosion Scythe", "Fury hammer", "Warrior Boots", "Wind of Nature"], "games": 2, "wins": 2, "wr": 1.0, "wlb": 0.3424}, {"items": ["Demon Hunter Sword", "Fury hammer", "Golden Staff", "Wind of Nature"], "games": 2, "wins": 2, "wr": 1.0, "wlb": 0.3424}, {"items": ["Demon Hunter Sword", "Fury hammer", "Warrior Boots", "Wind of Nature"], "games": 2, "wins": 2, "wr": 1.0, "wlb": 0.3424}, {"items": ["Fury hammer", "Golden Staff", "Warrior Boots", "Wind of Nature"], "games": 2, "wins": 2, "wr": 1.0, "wlb": 0.3424}, {"items": ["Corrosion Scythe", "Demon Hunter Sword", "Golden Staff", "Winter crown"], "games": 2, "wins": 2, "wr": 1.0, "wlb": 0.3424}, {"items": ["Corrosion Scythe", "Demon Hunter Sword", "Malefic Gun", "Winter crown"], "games": 2, "wins": 2, "wr": 1.0, "wlb": 0.3424}, {"items": ["Corrosion Scythe", "Golden Staff", "Malefic Gun", "Winter crown"], "games": 2, "wins": 2, "wr": 1.0, "wlb": 0.3424}, {"items": ["Demon Hunter Sword", "Golden Staff", "Malefic Gun", "Winter crown"], "games": 2, "wins": 2, "wr": 1.0, "wlb": 0.3424}, {"items": ["Corrosion Scythe", "Demon Hunter Sword", "Golden Staff", "Warrior Boots"], "games": 17, "wins": 9, "wr": 0.5294, "wlb": 0.3096}, {"items": ["Corrosion Scythe", "Demon Hunter Sword", "Golden Staff", "Tough Boots"], "games": 5, "wins": 3, "wr": 0.6, "wlb": 0.2307}, {"items": ["Corrosion Scythe", "Demon Hunter Sword", "Golden Staff", "Malefic Gun"], "games": 17, "wins": 7, "wr": 0.4118, "wlb": 0.2161}, {"items": ["Corrosion Scythe", "Malefic Gun", "Warrior Boots", "Wind of Nature"], "games": 3, "wins": 2, "wr": 0.6667, "wlb": 0.2077}, {"items": ["Demon Hunter Sword", "Malefic Gun", "Warrior Boots", "Wind of Nature"], "games": 3, "wins": 2, "wr": 0.6667, "wlb": 0.2077}, {"items": ["Golden Staff", "Malefic Gun", "Warrior Boots", "Wind of Nature"], "games": 3, "wins": 2, "wr": 0.6667, "wlb": 0.2077}], "5": [{"items": ["Corrosion Scythe", "Demon Hunter Sword", "Golden Staff", "Warrior Boots", "Wind of Nature"], "games": 11, "wins": 8, "wr": 0.7273, "wlb": 0.4343}, {"items": ["Corrosion Scythe", "Demon Hunter Sword", "Fury hammer", "Golden Staff", "Wind of Nature"], "games": 2, "wins": 2, "wr": 1.0, "wlb": 0.3424}, {"items": ["Corrosion Scythe", "Demon Hunter Sword", "Fury hammer", "Warrior Boots", "Wind of Nature"], "games": 2, "wins": 2, "wr": 1.0, "wlb": 0.3424}, {"items": ["Corrosion Scythe", "Fury hammer", "Golden Staff", "Warrior Boots", "Wind of Nature"], "games": 2, "wins": 2, "wr": 1.0, "wlb": 0.3424}, {"items": ["Demon Hunter Sword", "Fury hammer", "Golden Staff", "Warrior Boots", "Wind of Nature"], "games": 2, "wins": 2, "wr": 1.0, "wlb": 0.3424}, {"items": ["Corrosion Scythe", "Demon Hunter Sword", "Golden Staff", "Malefic Gun", "Winter crown"], "games": 2, "wins": 2, "wr": 1.0, "wlb": 0.3424}, {"items": ["Corrosion Scythe", "Demon Hunter Sword", "Malefic Gun", "Warrior Boots", "Wind of Nature"], "games": 3, "wins": 2, "wr": 0.6667, "wlb": 0.2077}, {"items": ["Corrosion Scythe", "Golden Staff", "Malefic Gun", "Warrior Boots", "Wind of Nature"], "games": 3, "wins": 2, "wr": 0.6667, "wlb": 0.2077}, {"items": ["Demon Hunter Sword", "Golden Staff", "Malefic Gun", "Warrior Boots", "Wind of Nature"], "games": 3, "wins": 2, "wr": 0.6667, "wlb": 0.2077}, {"items": ["Corrosion Scythe", "Demon Hunter Sword", "Golden Staff", "Rose Gold Meteor", "Warrior Boots"], "games": 3, "wins": 2, "wr": 0.6667, "wlb": 0.2077}, {"items": ["Corrosion Scythe", "Demon Hunter Sword", "Golden Staff", "Malefic Gun", "Warrior Boots"], "games": 6, "wins": 3, "wr": 0.5, "wlb": 0.1876}, {"items": ["Corrosion Scythe", "Demon Hunter Sword", "Golden Staff", "Malefic Gun", "Wind of Nature"], "games": 7, "wins": 3, "wr": 0.4286, "wlb": 0.1582}, {"items": ["Corrosion Scythe", "Demon Hunter Sword", "Fury hammer", "Golden Staff", "Warrior Boots"], "games": 4, "wins": 2, "wr": 0.5, "wlb": 0.15}, {"items": ["Corrosion Scythe", "Demon Hunter Sword", "Golden Staff", "Malefic Gun", "Tough Boots"], "games": 4, "wins": 2, "wr": 0.5, "wlb": 0.15}, {"items": ["Corrosion Scythe", "Demon Hunter Sword", "Golden Staff", "Malefic Gun", "Rose Gold Meteor"], "games": 9, "wins": 3, "wr": 0.3333, "wlb": 0.1206}, {"items": ["Corrosion Scythe", "Demon Hunter Sword", "Golden Staff", "Immortality", "Malefic Gun"], "games": 2, "wins": 1, "wr": 0.5, "wlb": 0.0945}, {"items": ["Corrosion Scythe", "Demon Hunter Sword", "Golden Staff", "Rose Gold Meteor", "Wind of Nature"], "games": 4, "wins": 1, "wr": 0.25, "wlb": 0.0456}, {"items": ["Corrosion Scythe", "Demon Hunter Sword", "Malefic Gun", "Rose Gold Meteor", "Wind of Nature"], "games": 3, "wins": 0, "wr": 0.0, "wlb": 0.0}, {"items": ["Corrosion Scythe", "Golden Staff", "Malefic Gun", "Rose Gold Meteor", "Wind of Nature"], "games": 3, "wins": 0, "wr": 0.0, "wlb": 0.0}, {"items": ["Demon Hunter Sword", "Golden Staff", "Malefic Gun", "Rose Gold Meteor", "Wind of Nature"], "games": 3, "wins": 0, "wr": 0.0, "wlb": 0.0}], "6": [{"items": ["Corrosion Scythe", "Demon Hunter Sword", "Fury hammer", "Golden Staff", "Warrior Boots", "Wind of Nature"], "games": 2, "wins": 2, "wr": 1.0, "wlb": 0.3424}, {"items": ["Corrosion Scythe", "Demon Hunter Sword", "Golden Staff", "Malefic Gun", "Warrior Boots", "Wind of Nature"], "games": 3, "wins": 2, "wr": 0.6667, "wlb": 0.2077}, {"items": ["Corrosion Scythe", "Demon Hunter Sword", "Golden Staff", "Malefic Gun", "Rose Gold Meteor", "Wind of Nature"], "games": 3, "wins": 0, "wr": 0.0, "wlb": 0.0}, {"items": ["Corrosion Scythe", "Dagger", "Demon Hunter Sword", "Golden Staff", "Warrior Boots", "Wind of Nature"], "games": 2, "wins": 0, "wr": 0.0, "wlb": 0.0}]}, "emblems": [{"id": "20007", "name": "Fighter", "games": 30, "wins": 14, "wr": 0.4667, "wlb": 0.3023}], "talents": [{"id": "132", "name": "Quantum Charge", "class": "Basic Common", "type": "core", "games": 30, "wins": 14, "wr": 0.4667, "wlb": 0.3023}, {"id": "112", "name": "Swift", "class": "Basic Common", "type": "standard", "games": 27, "wins": 12, "wr": 0.4444, "wlb": 0.2759}, {"id": "721", "name": "Festival of Blood", "class": "Fighter", "type": "standard", "games": 22, "wins": 10, "wr": 0.4545, "wlb": 0.2692}, {"id": "521", "name": "Master Assassin", "class": "Assassin", "type": "standard", "games": 8, "wins": 4, "wr": 0.5, "wlb": 0.2152}, {"id": "111", "name": "Thrill", "class": "Basic Common", "type": "standard", "games": 3, "wins": 2, "wr": 0.6667, "wlb": 0.2077}], "emblem_talent_combos": [{"emblem_id": "20007", "emblem": "Fighter", "talents": [{"id": "112", "name": "Swift"}, {"id": "132", "name": "Quantum Charge"}, {"id": "721", "name": "Festival of Blood"}], "games": 20, "wins": 9, "wr": 0.45, "wlb": 0.2582}, {"emblem_id": "20007", "emblem": "Fighter", "talents": [{"id": "112", "name": "Swift"}, {"id": "132", "name": "Quantum Charge"}, {"id": "521", "name": "Master Assassin"}], "games": 7, "wins": 3, "wr": 0.4286, "wlb": 0.1582}, {"emblem_id": "20007", "emblem": "Fighter", "talents": [{"id": "111", "name": "Thrill"}, {"id": "132", "name": "Quantum Charge"}, {"id": "721", "name": "Festival of Blood"}], "games": 2, "wins": 1, "wr": 0.5, "wlb": 0.0945}], "players": [{"name": "Kyouu", "games": 7, "wins": 4, "wr": 0.5714, "wlb": 0.2505, "top_build": ["Corrosion Scythe", "Demon Hunter Sword", "Golden Staff", "Immortality", "Malefic Gun", "Rose Gold Meteor"], "top_emblem": "Fighter", "top_talents": [{"id": "112", "name": "Swift"}, {"id": "132", "name": "Quantum Charge"}, {"id": "721", "name": "Festival of Blood"}]}, {"name": "SuperMarco", "games": 3, "wins": 2, "wr": 0.6667, "wlb": 0.2077, "top_build": ["Corrosion Scythe", "Demon Hunter Sword", "Golden Staff", "Malefic Gun", "Regular Spear", "Tough Boots"], "top_emblem": "Fighter", "top_talents": [{"id": "112", "name": "Swift"}, {"id": "132", "name": "Quantum Charge"}, {"id": "521", "name": "Master Assassin"}]}, {"name": "Netskie", "games": 3, "wins": 1, "wr": 0.3333, "wlb": 0.0615, "top_build": ["Corrosion Scythe", "Demon Hunter Sword", "Golden Staff", "Rose Gold Meteor", "Warrior Boots", "Wind of Nature"], "top_emblem": "Fighter", "top_talents": [{"id": "112", "name": "Swift"}, {"id": "132", "name": "Quantum Charge"}, {"id": "721", "name": "Festival of Blood"}]}, {"name": "Maybeee", "games": 2, "wins": 1, "wr": 0.5, "wlb": 0.0945, "top_build": ["Corrosion Scythe", "Demon Hunter Sword", "Fury hammer", "Golden Staff", "Warrior Boots", "Wind of Nature"], "top_emblem": "Fighter", "top_talents": [{"id": "112", "name": "Swift"}, {"id": "132", "name": "Quantum Charge"}, {"id": "721", "name": "Festival of Blood"}]}, {"name": "Owl.", "games": 2, "wins": 1, "wr": 0.5, "wlb": 0.0945, "top_build": ["Corrosion Scythe", "Demon Hunter Sword", "Golden Staff", "Vitality Crystal", "Warrior Boots", "Wind of Nature"], "top_emblem": "Fighter", "top_talents": [{"id": "112", "name": "Swift"}, {"id": "132", "name": "Quantum Charge"}, {"id": "721", "name": "Festival of Blood"}]}, {"name": "Teddy", "games": 2, "wins": 1, "wr": 0.5, "wlb": 0.0945, "top_build": ["Corrosion Scythe", "Demon Hunter Sword", "Golden Staff", "Malefic Gun", "Warrior Boots", "Wind of Nature"], "top_emblem": "Fighter", "top_talents": [{"id": "112", "name": "Swift"}, {"id": "132", "name": "Quantum Charge"}, {"id": "721", "name": "Festival of Blood"}]}, {"name": "shizou", "games": 2, "wins": 0, "wr": 0.0, "wlb": 0.0, "top_build": ["Corrosion Scythe", "Demon Hunter Sword", "Golden Staff", "Malefic Gun", "Regular Spear", "Warrior Boots"], "top_emblem": "Fighter", "top_talents": [{"id": "112", "name": "Swift"}, {"id": "132", "name": "Quantum Charge"}, {"id": "721", "name": "Festival of Blood"}]}, {"name": "Kelra", "games": 1, "wins": 1, "wr": 1.0, "wlb": 0.2065, "top_build": ["Corrosion Scythe", "Demon Hunter Sword", "Golden Staff", "Warrior Boots", "Wind of Nature"], "top_emblem": "Fighter", "top_talents": [{"id": "112", "name": "Swift"}, {"id": "132", "name": "Quantum Charge"}, {"id": "721", "name": "Festival of Blood"}]}, {"name": "Kuroky.", "games": 1, "wins": 1, "wr": 1.0, "wlb": 0.2065, "top_build": ["Corrosion Scythe", "Demon Hunter Sword", "Golden Staff", "Malefic Gun", "Warrior Boots", "Wind of Nature"], "top_emblem": "Fighter", "top_talents": [{"id": "112", "name": "Swift"}, {"id": "132", "name": "Quantum Charge"}, {"id": "521", "name": "Master Assassin"}]}, {"name": "Daiki_", "games": 1, "wins": 1, "wr": 1.0, "wlb": 0.2065, "top_build": ["Corrosion Scythe", "Demon Hunter Sword", "Golden Staff", "Magic Blade", "Tough Boots"], "top_emblem": "Fighter", "top_talents": [{"id": "111", "name": "Thrill"}, {"id": "132", "name": "Quantum Charge"}, {"id": "521", "name": "Master Assassin"}]}, {"name": "Domengkite", "games": 1, "wins": 1, "wr": 1.0, "wlb": 0.2065, "top_build": ["Corrosion Scythe", "Demon Hunter Sword", "Golden Staff", "Malefic Gun", "Tough Boots", "Winter crown"], "top_emblem": "Fighter", "top_talents": [{"id": "111", "name": "Thrill"}, {"id": "132", "name": "Quantum Charge"}, {"id": "721", "name": "Festival of Blood"}]}, {"name": "SuperToYy", "games": 1, "wins": 0, "wr": 0.0, "wlb": 0.0, "top_build": ["Corrosion Scythe", "Demon Hunter Sword", "Fury hammer", "Golden Staff", "Warrior Boots"], "top_emblem": "Fighter", "top_talents": [{"id": "111", "name": "Thrill"}, {"id": "132", "name": "Quantum Charge"}, {"id": "721", "name": "Festival of Blood"}]}, {"name": "Xyve", "games": 1, "wins": 0, "wr": 0.0, "wlb": 0.0, "top_build": ["Corrosion Scythe", "Demon Hunter Sword", "Golden Staff", "Malefic Gun", "Rose Gold Meteor", "Wind of Nature"], "top_emblem": "Fighter", "top_talents": [{"id": "112", "name": "Swift"}, {"id": "132", "name": "Quantum Charge"}, {"id": "521", "name": "Master Assassin"}]}, {"name": "Erlan", "games": 1, "wins": 0, "wr": 0.0, "wlb": 0.0, "top_build": ["Corrosion Scythe", "Demon Hunter Sword", "Golden Staff", "Immortality", "Malefic Gun", "Warrior Boots"], "top_emblem": "Fighter", "top_talents": [{"id": "112", "name": "Swift"}, {"id": "132", "name": "Quantum Charge"}, {"id": "521", "name": "Master Assassin"}]}, {"name": "Nosia", "games": 1, "wins": 0, "wr": 0.0, "wlb": 0.0, "top_build": ["Corrosion Scythe", "Dagger", "Demon Hunter Sword", "Golden Staff", "Warrior Boots", "Wind of Nature"], "top_emblem": "Fighter", "top_talents": [{"id": "112", "name": "Swift"}, {"id": "132", "name": "Quantum Charge"}, {"id": "721", "name": "Festival of Blood"}]}, {"name": "Bennyqt", "games": 1, "wins": 0, "wr": 0.0, "wlb": 0.0, "top_build": ["Corrosion Scythe", "Demon Hunter Sword", "Golden Staff", "Malefic Gun", "Rose Gold Meteor", "Wind of Nature"], "top_emblem": "Fighter", "top_talents": [{"id": "112", "name": "Swift"}, {"id": "132", "name": "Quantum Charge"}, {"id": "521", "name": "Master Assassin"}]}], "name": "Karrie", "slug": "karrie", "portrait": "img/heroes/karrie.png", "hero_id": "40"}