{"total_games": 45, "wins": 23, "wr": 0.5111, "items": [{"id": "2208", "name": "Queen's Wings", "games": 26, "wins": 17, "wr": 0.6538, "wlb": 0.4622}, {"id": "3001", "name": "Malefic Roar", "games": 21, "wins": 14, "wr": 0.6667, "wlb": 0.4537}, {"id": "3004", "name": "Endless Battle", "games": 37, "wins": 20, "wr": 0.5405, "wlb": 0.3838}, {"id": "1615180828774", "name": "War Axe", "games": 45, "wins": 23, "wr": 0.5111, "wlb": 0.37}, {"id": "3422", "name": "Flame Hunter's Tough Boots", "games": 38, "wins": 19, "wr": 0.5, "wlb": 0.3485}, {"id": "3208", "name": "Brute Force Breastplate", "games": 36, "wins": 18, "wr": 0.5, "wlb": 0.3447}, {"id": "3009", "name": "Hunter Strike", "games": 4, "wins": 3, "wr": 0.75, "wlb": 0.3006}, {"id": "3012", "name": "Rose Gold Meteor", "games": 7, "wins": 4, "wr": 0.5714, "wlb": 0.2505}, {"id": "3008", "name": "Blade of Despair", "games": 3, "wins": 2, "wr": 0.6667, "wlb": 0.2077}, {"id": "2005", "name": "Magic Blade", "games": 1, "wins": 1, "wr": 1.0, "wlb": 0.2065}, {"id": "1620344127331", "name": "Winter crown", "games": 1, "wins": 1, "wr": 1.0, "wlb": 0.2065}, {"id": "3005", "name": "Windtalker", "games": 1, "wins": 1, "wr": 1.0, "wlb": 0.2065}, {"id": "2008", "name": "Corrosion Scythe", "games": 1, "wins": 1, "wr": 1.0, "wlb": 0.2065}, {"id": "3421", "name": "Ice Hunter's Tough Boots", "games": 6, "wins": 3, "wr": 0.5, "wlb": 0.1876}, {"id": "2004", "name": "Fury hammer", "games": 8, "wins": 3, "wr": 0.375, "wlb": 0.1368}, {"id": "3207", "name": "Immortality", "games": 2, "wins": 1, "wr": 0.5, "wlb": 0.0945}, {"id": "1205", "name": "Hero's Ring", "games": 2, "wins": 1, "wr": 0.5, "wlb": 0.0945}, {"id": "2201", "name": "Ares Belt", "games": 3, "wins": 1, "wr": 0.3333, "wlb": 0.0615}, {"id": "3210", "name": "Radiant Armor", "games": 3, "wins": 1, "wr": 0.3333, "wlb": 0.0615}, {"id": "2001", "name": "Legion Sword", "games": 4, "wins": 1, "wr": 0.25, "wlb": 0.0456}, {"id": "1005", "name": "Iron Hunting Bow", "games": 2, "wins": 0, "wr": 0.0, "wlb": 0.0}, {"id": "2103", "name": "Azure Blade", "games": 2, "wins": 0, "wr": 0.0, "wlb": 0.0}, {"id": "2002", "name": "Ogre Tomahawk", "games": 1, "wins": 0, "wr": 0.0, "wlb": 0.0}, {"id": "1001", "name": "Dagger", "games": 1, "wins": 0, "wr": 0.0, "wlb": 0.0}], "item_combos": {"3": [{"items": ["Endless Battle", "Malefic Roar", "Queen's Wings"], "games": 14, "wins": 11, "wr": 0.7857, "wlb": 0.5241}, {"items": ["Malefic Roar", "Queen's Wings", "War Axe"], "games": 14, "wins": 11, "wr": 0.7857, "wlb": 0.5241}, {"items": ["Brute Force Breastplate", "Malefic Roar", "Queen's Wings"], "games": 13, "wins": 10, "wr": 0.7692, "wlb": 0.4974}, {"items": ["Flame Hunter's Tough Boots", "Malefic Roar", "Queen's Wings"], "games": 12, "wins": 9, "wr": 0.75, "wlb": 0.4677}, {"items": ["Endless Battle", "Queen's Wings", "War Axe"], "games": 24, "wins": 16, "wr": 0.6667, "wlb": 0.4671}, {"items": ["Brute Force Breastplate", "Queen's Wings", "War Axe"], "games": 19, "wins": 13, "wr": 0.6842, "wlb": 0.4601}, {"items": ["Endless Battle", "Malefic Roar", "War Axe"], "games": 21, "wins": 14, "wr": 0.6667, "wlb": 0.4537}, {"items": ["Endless Battle", "Ice Hunter's Tough Boots", "War Axe"], "games": 3, "wins": 3, "wr": 1.0, "wlb": 0.4385}, {"items": ["Brute Force Breastplate", "Endless Battle", "Queen's Wings"], "games": 18, "wins": 12, "wr": 0.6667, "wlb": 0.4375}, {"items": ["Flame Hunter's Tough Boots", "Queen's Wings", "War Axe"], "games": 22, "wins": 14, "wr": 0.6364, "wlb": 0.4295}, {"items": ["Brute Force Breastplate", "Flame Hunter's Tough Boots", "Queen's Wings"], "games": 17, "wins": 11, "wr": 0.6471, "wlb": 0.413}, {"items": ["Brute Force Breastplate", "Endless Battle", "Malefic Roar"], "games": 19, "wins": 12, "wr": 0.6316, "wlb": 0.4104}, {"items": ["Brute Force Breastplate", "Malefic Roar", "War Axe"], "games": 19, "wins": 12, "wr": 0.6316, "wlb": 0.4104}, {"items": ["Endless Battle", "Flame Hunter's Tough Boots", "Malefic Roar"], "games": 19, "wins": 12, "wr": 0.6316, "wlb": 0.4104}, {"items": ["Flame Hunter's Tough Boots", "Malefic Roar", "War Axe"], "games": 19, "wins": 12, "wr": 0.6316, "wlb": 0.4104}, {"items": ["Endless Battle", "Flame Hunter's Tough Boots", "Queen's Wings"], "games": 21, "wins": 13, "wr": 0.619, "wlb": 0.4088}, {"items": ["Endless Battle", "Queen's Wings", "Rose Gold Meteor"], "games": 5, "wins": 4, "wr": 0.8, "wlb": 0.3755}, {"items": ["Brute Force Breastplate", "Flame Hunter's Tough Boots", "Malefic Roar"], "games": 17, "wins": 10, "wr": 0.5882, "wlb": 0.3601}, {"items": ["Brute Force Breastplate", "Endless Battle", "War Axe"], "games": 29, "wins": 15, "wr": 0.5172, "wlb": 0.3443}, {"items": ["Endless Battle", "Malefic Roar", "Rose Gold Meteor"], "games": 2, "wins": 2, "wr": 1.0, "wlb": 0.3424}], "4": [{"items": ["Endless Battle", "Malefic Roar", "Queen's Wings", "War Axe"], "games": 14, "wins": 11, "wr": 0.7857, "wlb": 0.5241}, {"items": ["Brute Force Breastplate", "Endless Battle", "Malefic Roar", "Queen's Wings"], "games": 13, "wins": 10, "wr": 0.7692, "wlb": 0.4974}, {"items": ["Brute Force Breastplate", "Malefic Roar", "Queen's Wings", "War Axe"], "games": 13, "wins": 10, "wr": 0.7692, "wlb": 0.4974}, {"items": ["Endless Battle", "Flame Hunter's Tough Boots", "Malefic Roar", "Queen's Wings"], "games": 12, "wins": 9, "wr": 0.75, "wlb": 0.4677}, {"items": ["Flame Hunter's Tough Boots", "Malefic Roar", "Queen's Wings", "War Axe"], "games": 12, "wins": 9, "wr": 0.75, "wlb": 0.4677}, {"items": ["Brute Force Breastplate", "Endless Battle", "Queen's Wings", "War Axe"], "games": 18, "wins": 12, "wr": 0.6667, "wlb": 0.4375}, {"items": ["Brute Force Breastplate", "Flame Hunter's Tough Boots", "Malefic Roar", "Queen's Wings"], "games": 11, "wins": 8, "wr": 0.7273, "wlb": 0.4343}, {"items": ["Brute Force Breastplate", "Flame Hunter's Tough Boots", "Queen's Wings", "War Axe"], "games": 17, "wins": 11, "wr": 0.6471, "wlb": 0.413}, {"items": ["Brute Force Breastplate", "Endless Battle", "Malefic Roar", "War Axe"], "games": 19, "wins": 12, "wr": 0.6316, "wlb": 0.4104}, {"items": ["Endless Battle", "Flame Hunter's Tough Boots", "Malefic Roar", "War Axe"], "games": 19, "wins": 12, "wr": 0.6316, "wlb": 0.4104}, {"items": ["Endless Battle", "Flame Hunter's Tough Boots", "Queen's Wings", "War Axe"], "games": 21, "wins": 13, "wr": 0.619, "wlb": 0.4088}, {"items": ["Brute Force Breastplate", "Endless Battle", "Flame Hunter's Tough Boots", "Queen's Wings"], "games": 16, "wins": 10, "wr": 0.625, "wlb": 0.3864}, {"items": ["Endless Battle", "Queen's Wings", "Rose Gold Meteor", "War Axe"], "games": 5, "wins": 4, "wr": 0.8, "wlb": 0.3755}, {"items": ["Brute Force Breastplate", "Endless Battle", "Flame Hunter's Tough Boots", "Malefic Roar"], "games": 17, "wins": 10, "wr": 0.5882, "wlb": 0.3601}, {"items": ["Brute Force Breastplate", "Flame Hunter's Tough Boots", "Malefic Roar", "War Axe"], "games": 17, "wins": 10, "wr": 0.5882, "wlb": 0.3601}, {"items": ["Endless Battle", "Malefic Roar", "Queen's Wings", "Rose Gold Meteor"], "games": 2, "wins": 2, "wr": 1.0, "wlb": 0.3424}, {"items": ["Endless Battle", "Malefic Roar", "Rose Gold Meteor", "War Axe"], "games": 2, "wins": 2, "wr": 1.0, "wlb": 0.3424}, {"items": ["Malefic Roar", "Queen's Wings", "Rose Gold Meteor", "War Axe"], "games": 2, "wins": 2, "wr": 1.0, "wlb": 0.3424}, {"items": ["Brute Force Breastplate", "Endless Battle", "Ice Hunter's Tough Boots", "War Axe"], "games": 2, "wins": 2, "wr": 1.0, "wlb": 0.3424}, {"items": ["Endless Battle", "Ice Hunter's Tough Boots", "Queen's Wings", "War Axe"], "games": 2, "wins": 2, "wr": 1.0, "wlb": 0.3424}], "5": [{"items": ["Brute Force Breastplate", "Endless Battle", "Malefic Roar", "Queen's Wings", "War Axe"], "games": 13, "wins": 10, "wr": 0.7692, "wlb": 0.4974}, {"items": ["Endless Battle", "Flame Hunter's Tough Boots", "Malefic Roar", "Queen's Wings", "War Axe"], "games": 12, "wins": 9, "wr": 0.75, "wlb": 0.4677}, {"items": ["Brute Force Breastplate", "Endless Battle", "Flame Hunter's Tough Boots", "Malefic Roar", "Queen's Wings"], "games": 11, "wins": 8, "wr": 0.7273, "wlb": 0.4343}, {"items": ["Brute Force Breastplate", "Flame Hunter's Tough Boots", "Malefic Roar", "Queen's Wings", "War Axe"], "games": 11, "wins": 8, "wr": 0.7273, "wlb": 0.4343}, {"items": ["Brute Force Breastplate", "Endless Battle", "Flame Hunter's Tough Boots", "Queen's Wings", "War Axe"], "games": 16, "wins": 10, "wr": 0.625, "wlb": 0.3864}, {"items": ["Brute Force Breastplate", "Endless Battle", "Flame Hunter's Tough Boots", "Malefic Roar", "War Axe"], "games": 17, "wins": 10, "wr": 0.5882, "wlb": 0.3601}, {"items": ["Endless Battle", "Malefic Roar", "Queen's Wings", "Rose Gold Meteor", "War Axe"], "games": 2, "wins": 2, "wr": 1.0, "wlb": 0.3424}, {"items": ["Endless Battle", "Flame Hunter's Tough Boots", "Hunter Strike", "Malefic Roar", "War Axe"], "games": 2, "wins": 2, "wr": 1.0, "wlb": 0.3424}, {"items": ["Endless Battle", "Flame Hunter's Tough Boots", "Queen's Wings", "Rose Gold Meteor", "War Axe"], "games": 4, "wins": 3, "wr": 0.75, "wlb": 0.3006}, {"items": ["Brute Force Breastplate", "Endless Battle", "Flame Hunter's Tough Boots", "Legion Sword", "Queen's Wings"], "games": 1, "wins": 1, "wr": 1.0, "wlb": 0.2065}, {"items": ["Brute Force Breastplate", "Endless Battle", "Legion Sword", "Queen's Wings", "War Axe"], "games": 1, "wins": 1, "wr": 1.0, "wlb": 0.2065}, {"items": ["Brute Force Breastplate", "Flame Hunter's Tough Boots", "Legion Sword", "Queen's Wings", "War Axe"], "games": 1, "wins": 1, "wr": 1.0, "wlb": 0.2065}, {"items": ["Endless Battle", "Flame Hunter's Tough Boots", "Legion Sword", "Queen's Wings", "War Axe"], "games": 1, "wins": 1, "wr": 1.0, "wlb": 0.2065}, {"items": ["Blade of Despair", "Brute Force Breastplate", "Flame Hunter's Tough Boots", "Immortality", "War Axe"], "games": 1, "wins": 1, "wr": 1.0, "wlb": 0.2065}, {"items": ["Endless Battle", "Flame Hunter's Tough Boots", "Fury hammer", "Queen's Wings", "Rose Gold Meteor"], "games": 1, "wins": 1, "wr": 1.0, "wlb": 0.2065}, {"items": ["Endless Battle", "Flame Hunter's Tough Boots", "Fury hammer", "Rose Gold Meteor", "War Axe"], "games": 1, "wins": 1, "wr": 1.0, "wlb": 0.2065}, {"items": ["Endless Battle", "Fury hammer", "Queen's Wings", "Rose Gold Meteor", "War Axe"], "games": 1, "wins": 1, "wr": 1.0, "wlb": 0.2065}, {"items": ["Flame Hunter's Tough Boots", "Fury hammer", "Queen's Wings", "Rose Gold Meteor", "War Axe"], "games": 1, "wins": 1, "wr": 1.0, "wlb": 0.2065}, {"items": ["Brute Force Breastplate", "Endless Battle", "Malefic Roar", "Queen's Wings", "Rose Gold Meteor"], "games": 1, "wins": 1, "wr": 1.0, "wlb": 0.2065}, {"items": ["Brute Force Breastplate", "Endless Battle", "Malefic Roar", "Rose Gold Meteor", "War Axe"], "games": 1, "wins": 1, "wr": 1.0, "wlb": 0.2065}], "6": [{"items": ["Brute Force Breastplate", "Endless Battle", "Flame Hunter's Tough Boots", "Malefic Roar", "Queen's Wings", "War Axe"], "games": 11, "wins": 8, "wr": 0.7273, "wlb": 0.4343}, {"items": ["Brute Force Breastplate", "Endless Battle", "Flame Hunter's Tough Boots", "Legion Sword", "Queen's Wings", "War Axe"], "games": 1, "wins": 1, "wr": 1.0, "wlb": 0.2065}, {"items": ["Endless Battle", "Flame Hunter's Tough Boots", "Fury hammer", "Queen's Wings", "Rose Gold Meteor", "War Axe"], "games": 1, "wins": 1, "wr": 1.0, "wlb": 0.2065}, {"items": ["Brute Force Breastplate", "Endless Battle", "Malefic Roar", "Queen's Wings", "Rose Gold Meteor", "War Axe"], "games": 1, "wins": 1, "wr": 1.0, "wlb": 0.2065}, {"items": ["Endless Battle", "Flame Hunter's Tough Boots", "Malefic Roar", "Queen's Wings", "Rose Gold Meteor", "War Axe"], "games": 1, "wins": 1, "wr": 1.0, "wlb": 0.2065}, {"items": ["Blade of Despair", "Brute Force Breastplate", "Endless Battle", "Flame Hunter's Tough Boots", "Malefic Roar", "War Axe"], "games": 1, "wins": 1, "wr": 1.0, "wlb": 0.2065}, {"items": ["Brute Force Breastplate", "Flame Hunter's Tough Boots", "Magic Blade", "Queen's Wings", "War Axe", "Winter crown"], "games": 1, "wins": 1, "wr": 1.0, "wlb": 0.2065}, {"items": ["Endless Battle", "Flame Hunter's Tough Boots", "Queen's Wings", "Radiant Armor", "Rose Gold Meteor", "War Axe"], "games": 1, "wins": 1, "wr": 1.0, "wlb": 0.2065}, {"items": ["Brute Force Breastplate", "Endless Battle", "Ice Hunter's Tough Boots", "Malefic Roar", "Queen's Wings", "War Axe"], "games": 1, "wins": 1, "wr": 1.0, "wlb": 0.2065}, {"items": ["Endless Battle", "Flame Hunter's Tough Boots", "Hunter Strike", "Malefic Roar", "War Axe", "Windtalker"], "games": 1, "wins": 1, "wr": 1.0, "wlb": 0.2065}, {"items": ["Corrosion Scythe", "Endless Battle", "Hunter Strike", "Ice Hunter's Tough Boots", "Queen's Wings", "War Axe"], "games": 1, "wins": 1, "wr": 1.0, "wlb": 0.2065}, {"items": ["Brute Force Breastplate", "Endless Battle", "Flame Hunter's Tough Boots", "Hunter Strike", "Malefic Roar", "War Axe"], "games": 1, "wins": 1, "wr": 1.0, "wlb": 0.2065}, {"items": ["Brute Force Breastplate", "Endless Battle", "Flame Hunter's Tough Boots", "Fury hammer", "Queen's Wings", "War Axe"], "games": 2, "wins": 1, "wr": 0.5, "wlb": 0.0945}, {"items": ["Ares Belt", "Endless Battle", "Flame Hunter's Tough Boots", "Hero's Ring", "Rose Gold Meteor", "War Axe"], "games": 1, "wins": 0, "wr": 0.0, "wlb": 0.0}, {"items": ["Endless Battle", "Flame Hunter's Tough Boots", "Hunter Strike", "Queen's Wings", "Rose Gold Meteor", "War Axe"], "games": 1, "wins": 0, "wr": 0.0, "wlb": 0.0}, {"items": ["Fury hammer", "Ice Hunter's Tough Boots", "Queen's Wings", "Radiant Armor", "Rose Gold Meteor", "War Axe"], "games": 1, "wins": 0, "wr": 0.0, "wlb": 0.0}, {"items": ["Blade of Despair", "Brute Force Breastplate", "Endless Battle", "Flame Hunter's Tough Boots", "Queen's Wings", "War Axe"], "games": 1, "wins": 0, "wr": 0.0, "wlb": 0.0}, {"items": ["Brute Force Breastplate", "Endless Battle", "Flame Hunter's Tough Boots", "Legion Sword", "Malefic Roar", "War Axe"], "games": 1, "wins": 0, "wr": 0.0, "wlb": 0.0}, {"items": ["Brute Force Breastplate", "Endless Battle", "Flame Hunter's Tough Boots", "Immortality", "Malefic Roar", "War Axe"], "games": 1, "wins": 0, "wr": 0.0, "wlb": 0.0}, {"items": ["Azure Blade", "Brute Force Breastplate", "Dagger", "Fury hammer", "Ice Hunter's Tough Boots", "War Axe"], "games": 1, "wins": 0, "wr": 0.0, "wlb": 0.0}]}, "emblems": [{"id": "20005", "name": "Assassin", "games": 41, "wins": 22, "wr": 0.5366, "wlb": 0.3875}, {"id": "20012", "name": "Marksman", "games": 4, "wins": 1, "wr": 0.25, "wlb": 0.0456}], "talents": [{"id": "122", "name": "Seasoned Hunter", "class": "Basic Common", "type": "standard", "games": 45, "wins": 23, "wr": 0.5111, "wlb": 0.37}, {"id": "531", "name": "Killing Spree", "class": "Assassin", "type": "core", "games": 45, "wins": 23, "wr": 0.5111, "wlb": 0.37}, {"id": "112", "name": "Swift", "class": "Basic Common", "type": "standard", "games": 35, "wins": 18, "wr": 0.5143, "wlb": 0.3557}, {"id": "111", "name": "Thrill", "class": "Basic Common", "type": "standard", "games": 6, "wins": 3, "wr": 0.5, "wlb": 0.1876}, {"id": "511", "name": "Rapture", "class": "Assassin", "type": "standard", "games": 4, "wins": 2, "wr": 0.5, "wlb": 0.15}], "emblem_talent_combos": [{"emblem_id": "20005", "emblem": "Assassin", "talents": [{"id": "112", "name": "Swift"}, {"id": "122", "name": "Seasoned Hunter"}, {"id": "531", "name": "Killing Spree"}], "games": 35, "wins": 18, "wr": 0.5143, "wlb": 0.3557}, {"emblem_id": "20005", "emblem": "Assassin", "talents": [{"id": "111", "name": "Thrill"}, {"id": "122", "name": "Seasoned Hunter"}, {"id": "531", "name": "Killing Spree"}], "games": 5, "wins": 3, "wr": 0.6, "wlb": 0.2307}, {"emblem_id": "20005", "emblem": "Assassin", "talents": [{"id": "122", "name": "Seasoned Hunter"}, {"id": "511", "name": "Rapture"}, {"id": "531", "name": "Killing Spree"}], "games": 1, "wins": 1, "wr": 1.0, "wlb": 0.2065}, {"emblem_id": "20012", "emblem": "Marksman", "talents": [{"id": "122", "name": "Seasoned Hunter"}, {"id": "511", "name": "Rapture"}, {"id": "531", "name": "Killing Spree"}], "games": 3, "wins": 1, "wr": 0.3333, "wlb": 0.0615}, {"emblem_id": "20012", "emblem": "Marksman", "talents": [{"id": "111", "name": "Thrill"}, {"id": "122", "name": "Seasoned Hunter"}, {"id": "531", "name": "Killing Spree"}], "games": 1, "wins": 0, "wr": 0.0, "wlb": 0.0}], "players": [{"name": "Nnael", "games": 7, "wins": 4, "wr": 0.5714, "wlb": 0.2505, "top_build": ["Brute Force Breastplate", "Endless Battle", "Flame Hunter's Tough Boots", "Legion Sword", "Queen's Wings", "War Axe"], "top_emblem": "Assassin", "top_talents": [{"id": "112", "name": "Swift"}, {"id": "122", "name": "Seasoned Hunter"}, {"id": "531", "name": "Killing Spree"}]}, {"name": "Maykids", "games": 5, "wins": 4, "wr": 0.8, "wlb": 0.3755, "top_build": ["Brute Force Breastplate", "Endless Battle", "Malefic Roar", "Queen's Wings", "Rose Gold Meteor", "War Axe"], "top_emblem": "Assassin", "top_talents": [{"id": "112", "name": "Swift"}, {"id": "122", "name": "Seasoned Hunter"}, {"id": "531", "name": "Killing Spree"}]}, {"name": "Yazukee", "games": 4, "wins": 3, "wr": 0.75, "wlb": 0.3006, "top_build": ["Brute Force Breastplate", "Endless Battle", "Flame Hunter's Tough Boots", "Malefic Roar", "Queen's Wings", "War Axe"], "top_emblem": "Assassin", "top_talents": [{"id": "112", "name": "Swift"}, {"id": "122", "name": "Seasoned Hunter"}, {"id": "531", "name": "Killing Spree"}]}, {"name": "MPtheKing.", "games": 4, "wins": 1, "wr": 0.25, "wlb": 0.0456, "top_build": ["Brute Force Breastplate", "Endless Battle", "Flame Hunter's Tough Boots", "Malefic Roar", "Queen's Wings", "War Axe"], "top_emblem": "Marksman", "top_talents": [{"id": "122", "name": "Seasoned Hunter"}, {"id": "511", "name": "Rapture"}, {"id": "531", "name": "Killing Spree"}]}, {"name": "K1NGKONG", "games": 4, "wins": 1, "wr": 0.25, "wlb": 0.0456, "top_build": ["Brute Force Breastplate", "Endless Battle", "Flame Hunter's Tough Boots", "Malefic Roar", "Queen's Wings", "War Axe"], "top_emblem": "Assassin", "top_talents": [{"id": "112", "name": "Swift"}, {"id": "122", "name": "Seasoned Hunter"}, {"id": "531", "name": "Killing Spree"}]}, {"name": "KarlTzy", "games": 3, "wins": 3, "wr": 1.0, "wlb": 0.4385, "top_build": ["Brute Force Breastplate", "Endless Battle", "Flame Hunter's Tough Boots", "Malefic Roar", "Queen's Wings", "War Axe"], "top_emblem": "Assassin", "top_talents": [{"id": "111", "name": "Thrill"}, {"id": "122", "name": "Seasoned Hunter"}, {"id": "531", "name": "Killing Spree"}]}, {"name": "Alberttt", "games": 3, "wins": 2, "wr": 0.6667, "wlb": 0.2077, "top_build": ["Brute Force Breastplate", "Endless Battle", "Flame Hunter's Tough Boots", "Malefic Roar", "Queen's Wings", "War Axe"], "top_emblem": "Assassin", "top_talents": [{"id": "112", "name": "Swift"}, {"id": "122", "name": "Seasoned Hunter"}, {"id": "531", "name": "Killing Spree"}]}, {"name": "Andoryuuu", "games": 3, "wins": 1, "wr": 0.3333, "wlb": 0.0615, "top_build": ["Endless Battle", "Flame Hunter's Tough Boots", "Fury hammer", "Queen's Wings", "Rose Gold Meteor", "War Axe"], "top_emblem": "Assassin", "top_talents": [{"id": "112", "name": "Swift"}, {"id": "122", "name": "Seasoned Hunter"}, {"id": "531", "name": "Killing Spree"}]}, {"name": "Raizen.", "games": 3, "wins": 1, "wr": 0.3333, "wlb": 0.0615, "top_build": ["Brute Force Breastplate", "Endless Battle", "Flame Hunter's Tough Boots", "Malefic Roar", "Queen's Wings", "War Axe"], "top_emblem": "Assassin", "top_talents": [{"id": "112", "name": "Swift"}, {"id": "122", "name": "Seasoned Hunter"}, {"id": "531", "name": "Killing Spree"}]}, {"name": "JamesPangks", "games": 2, "wins": 1, "wr": 0.5, "wlb": 0.0945, "top_build": ["Corrosion Scythe", "Endless Battle", "Hunter Strike", "Ice Hunter's Tough Boots", "Queen's Wings", "War Axe"], "top_emblem": "Assassin", "top_talents": [{"id": "122", "name": "Seasoned Hunter"}, {"id": "511", "name": "Rapture"}, {"id": "531", "name": "Killing Spree"}]}, {"name": "Kyle", "games": 2, "wins": 1, "wr": 0.5, "wlb": 0.0945, "top_build": ["Azure Blade", "Brute Force Breastplate", "Dagger", "Fury hammer", "Ice Hunter's Tough Boots", "War Axe"], "top_emblem": "Assassin", "top_talents": [{"id": "112", "name": "Swift"}, {"id": "122", "name": "Seasoned Hunter"}, {"id": "531", "name": "Killing Spree"}]}, {"name": "Zaida", "games": 2, "wins": 0, "wr": 0.0, "wlb": 0.0, "top_build": ["Azure Blade", "Brute Force Breastplate", "Flame Hunter's Tough Boots", "Iron Hunting Bow", "War Axe"], "top_emblem": "Assassin", "top_talents": [{"id": "112", "name": "Swift"}, {"id": "122", "name": "Seasoned Hunter"}, {"id": "531", "name": "Killing Spree"}]}, {"name": "Kevinn", "games": 1, "wins": 1, "wr": 1.0, "wlb": 0.2065, "top_build": ["Brute Force Breastplate", "Endless Battle", "Flame Hunter's Tough Boots", "Fury hammer", "Queen's Wings", "War Axe"], "top_emblem": "Assassin", "top_talents": [{"id": "112", "name": "Swift"}, {"id": "122", "name": "Seasoned Hunter"}, {"id": "531", "name": "Killing Spree"}]}, {"name": "SuperKenn", "games": 1, "wins": 0, "wr": 0.0, "wlb": 0.0, "top_build": ["Ares Belt", "Endless Battle", "Flame Hunter's Tough Boots", "Hero's Ring", "Rose Gold Meteor", "War Axe"], "top_emblem": "Assassin", "top_talents": [{"id": "111", "name": "Thrill"}, {"id": "122", "name": "Seasoned Hunter"}, {"id": "531", "name": "Killing Spree"}]}, {"name": "Demonkite", "games": 1, "wins": 0, "wr": 0.0, "wlb": 0.0, "top_build": ["Ares Belt", "Brute Force Breastplate", "Flame Hunter's Tough Boots", "War Axe"], "top_emblem": "Assassin", "top_talents": [{"id": "112", "name": "Swift"}, {"id": "122", "name": "Seasoned Hunter"}, {"id": "531", "name": "Killing Spree"}]}], "name": "Leomord", "slug": "leomord", "portrait": "img/heroes/leomord.png", "hero_id": "67"}