{"name": "Vexana", "slug": "vexana", "portrait": "img/heroes/vexana.png", "hero_id": "38", "total_games": 2, "wins": 1, "wr": 0.5, "matches": [{"d": "2026-04-10", "w": 1, "items": ["Arcane Boots", "Divine Glaive", "Magic Wand", "Magic Wand", "Glowing Wand", "Lightning Truncheon"], "eid": "20006", "e": "Mage", "t": [{"id": "611", "name": "Inspire", "class": "Mage", "type": "standard"}, {"id": "121", "name": "Wilderness Blessing", "class": "Basic Common", "type": "standard"}, {"id": "131", "name": "Impure Rage", "class": "Basic Common", "type": "core"}], "p": "S A N Z"}, {"d": "2026-03-27", "w": 0, "items": ["Divine Glaive", "Blood Wings", "Demon Shoes", "Glowing Wand", "Winter crown", "Wishing Lantern"], "eid": "20006", "e": "Mage", "t": [{"id": "511", "name": "Rapture", "class": "Assassin", "type": "standard"}, {"id": "121", "name": "Wilderness Blessing", "class": "Basic Common", "type": "standard"}, {"id": "131", "name": "Impure Rage", "class": "Basic Common", "type": "core"}], "p": "Minguin"}]}